Workbook
Name Air_Compressor: 'Task Master'!$G$741:$G$798
Name AssetList: 'Asset Register'!$A$2:$A$16
Name Automobile: 'Task Master'!$G$2:$G$168
Name CategoryList: Lists!$A$2:$A$5
Name Dozer: 'Task Master'!$G$571:$G$602
Name Earth_Moving_Machinery_General_PM_Engine: 'Task Master'!$G$523:$G$570
Name Electrical_Electronics: 'Task Master'!$G$799:$G$859
Name Excavator: 'Task Master'!$G$603:$G$626
Name Generator: 'Task Master'!$G$675:$G$740
Name Grader: 'Task Master'!$G$651:$G$674
Name Heavy: Lists!$C$2:$C$2
Name Heavy_Truck: 'Task Master'!$G$362:$G$522
Name Light: Lists!$B$2:$B$3
Name Loader: 'Task Master'!$G$627:$G$650
Name Machinery: Lists!$D$2:$D$6
Name MTypeList: Lists!$G$2:$G$4
Name Others: Lists!$E$2:$E$4
Name Pick_Up_Station_Wagon_Mini_Bus: 'Task Master'!$G$169:$G$361

Sheet Read Me
B2: FLEET MAINTENANCE & FINANCIAL MANAGEMENT SYSTEM
B3: Standardized task library, dependent dropdowns, operational KPIs, lease revenue, and trend dashboard
B6: HOW THIS WORKBOOK IS STRUCTURED
B7: Task Master | C7: 858 standardized maintenance tasks from your standards document: Category > Equipment Type > Maintenance Group > Maintenance Type (Preventive/Corrective/Overhaul, auto-derived from the Group) > Task. Feeds every dropdown in the workbook.
B8: Asset Register | C8: One row per physical asset: its Category/Equipment Type, make, year, fuel norm, and Lease Rate/Hour. Both logs below look up an asset's details from here by Asset ID -- update the rate once, and it is correct everywhere.
B9: Daily Operations Log | C9: One row per asset per day (or shift). This is where Availability %, Utilization %, Downtime, Fuel Variance, and Total Revenue (Operable Hours x Lease Rate/Hour) are tracked. Revenue is earned by an asset OPERATING, not by being serviced -- so it lives here, not in the Maintenance Log.
B10: Maintenance Log | C10: One row per repair/service event. Category, Equipment Type, and Task are cascading dropdowns from Task Master; Maintenance Group and Maintenance Type are pulled through automatically. This sheet tracks COST (parts/labor/other), not revenue.
B11: Dashboard | C11: KPIs and trend breakdowns built from the two logs: Productivity (Availability/Utilization), Downtime, Maintenance trend by Group/Type, Fuel & Financial (Revenue vs. Cost), and optimization flags. Formulas run out to row 500-1000, ready for real data.
B12: Lists | C12: Hidden helper sheet holding dropdown source lists and named ranges. No need to edit directly.
B14: CELL COLOR KEY
B15: Blue text | C15: Cells you type into.
B16: Black text | C16: Formulas -- do not overwrite, they calculate automatically.
B17: Light blue fill | C17: Dropdown cells (Category / Equipment Type / Task / Asset ID).
B19: KEY ASSUMPTIONS
B20: Total Revenue | C20: Operable Hours x Lease Rate/Hour, logged per day per asset in Daily Operations Log (column U).
B21: Maintenance Type | C21: Auto-derived from each task's Maintenance Group: groups containing "Overhaul" -> Overhaul; "General Service" or "Service Hours" or "Inspecting/Testing/Receiving" -> Preventive; everything else (Brakes, Engine, Radiator, Hydraulic, etc.) -> Corrective. Adjust the logic on Task Master if you want different rules.
B23: EXTENDING THE SYSTEM
B24: Adding tasks | C24: Insert new rows inside the correct Equipment Type block on Task Master (not at the very end) so the block stays contiguous -- ask me to update the named ranges after.
B25: Adding assets | C25: Add a row to Asset Register; it becomes selectable in both logs immediately.
B26: Adding log entries | C26: Just continue down either log -- dropdowns and formulas are already live (Daily Ops to row 500, Maintenance Log to row 1000).
B27: Task-level trend analysis | C27: Group/Type breakdowns are pre-built on the Dashboard. For a breakdown by individual task, insert a PivotTable from the Maintenance Log table once you have real data.

Sheet Task Master
A1: Item No. | B1: Category | C1: Equipment Type | D1: Equipment Type (Safe Key) | E1: Maintenance Group | F1: Maintenance Type | G1: Task Description | H1: Standard Time (Hrs) | I1: Technicians (Std) | J1: Billable Hours | K1: Lookup Key
A2: 1 | B2: Light | C2: Automobile | D2: Automobile | E2: I. General Service A = 5,000 KM | F2: Preventive | G2: Changing the Engine Oil & Oil filter | H2: 1.5 | I2: 1 | J2: 1.5 | K2: Automobile||Changing the Engine Oil & Oil filter
A3: 2 | B3: Light | C3: Automobile | D3: Automobile | E3: I. General Service A = 5,000 KM | F3: Preventive | G3: Change Fuel filter | H3: 0.5 | I3: 1 | J3: 0.5 | K3: Automobile||Change Fuel filter
A4: 3 | B4: Light | C4: Automobile | D4: Automobile | E4: I. General Service A = 5,000 KM | F4: Preventive | G4: Changing Air Cleaner | H4: 0.5 | I4: 1 | J4: 0.5 | K4: Automobile||Changing Air Cleaner
A5: 4 | B5: Light | C5: Automobile | D5: Automobile | E5: I. General Service A = 5,000 KM | F5: Preventive | G5: Inspection of all Fluids & top Upping | H5: 1 | I5: 1 | J5: 1 | K5: Automobile||Inspection of all Fluids & top Upping
A6: 5 | B6: Light | C6: Automobile | D6: Automobile | E6: I. General Service A = 5,000 KM | F6: Preventive | G6: Lubricating all hinges, locks & Latches | H6: 1.5 | I6: 1 | J6: 1.5 | K6: Automobile||Lubricating all hinges, locks & Latches
A7: 6 | B7: Light | C7: Automobile | D7: Automobile | E7: I. General Service A = 5,000 KM | F7: Preventive | G7: Inspection of relay end & tie rod ends and steering gear box, Steering Damper | H7: 2 | I7: 1 | J7: 2 | K7: Automobile||Inspection of relay end & tie rod ends and steering gear box, Steering Damper
A8: 7 | B8: Light | C8: Automobile | D8: Automobile | E8: I. General Service A = 5,000 KM | F8: Preventive | G8: Inspection of underbody parts, suspension and Propeller shaft center bearing & universal joint if any | H8: 1 | I8: 2 | J8: 2 | K8: Automobile||Inspection of underbody parts, suspension and Propeller shaft center bearing & universal joint if any
A9: 8 | B9: Light | C9: Automobile | D9: Automobile | E9: I. General Service A = 5,000 KM | F9: Preventive | G9: Inspection of belts and Hoses | H9: 0.5 | I9: 1 | J9: 0.5 | K9: Automobile||Inspection of belts and Hoses
A10: 9 | B10: Light | C10: Automobile | D10: Automobile | E10: I. General Service A = 5,000 KM | F10: Preventive | G10: Check Function of all lighting systems | H10: 0.5 | I10: 1 | J10: 0.5 | K10: Automobile||Check Function of all lighting systems
A11: 10 | B11: Light | C11: Automobile | D11: Automobile | E11: II. General Service B = 10,000 KM | F11: Preventive | G11: Perform all activities in General Service "A" | H11: 9 | I11: - | J11: 10 | K11: Automobile||Perform all activities in General Service "A"
A12: 11 | B12: Light | C12: Automobile | D12: Automobile | E12: II. General Service B = 10,000 KM | F12: Preventive | G12: Check the condition & Security of seat | H12: 1 | I12: 1 | J12: 1 | K12: Automobile||Check the condition & Security of seat
A13: 12 | B13: Light | C13: Automobile | D13: Automobile | E13: II. General Service B = 10,000 KM | F13: Preventive | G13: Check all suspension, Shock absorbers, Stabilizer Bushings & Arm Bushings | H13: 1 | I13: 1 | J13: 1 | K13: Automobile||Check all suspension, Shock absorbers, Stabilizer Bushings & Arm Bushings
A14: 13 | B14: Light | C14: Automobile | D14: Automobile | E14: II. General Service B = 10,000 KM | F14: Preventive | G14: Clean battery terminals | H14: 0.5 | I14: 1 | J14: 0.5 | K14: Automobile||Clean battery terminals
A15: 14 | B15: Light | C15: Automobile | D15: Automobile | E15: II. General Service B = 10,000 KM | F15: Preventive | G15: Check Exhaust system for leakage & Damage | H15: 1 | I15: 1 | J15: 1 | K15: Automobile||Check Exhaust system for leakage & Damage
A16: 15 | B16: Light | C16: Automobile | D16: Automobile | E16: II. General Service B = 10,000 KM | F16: Preventive | G16: Servicing /Checking Front & rear Brakes, Hoses, Lines and Hand Brakes | H16: 8 | I16: 2 | J16: 16 | K16: Automobile||Servicing /Checking Front & rear Brakes, Hoses, Lines and Hand Brakes
A17: 16 | B17: Light | C17: Automobile | D17: Automobile | E17: II. General Service B = 10,000 KM | F17: Preventive | G17: Lubricating Front Wheel Hub Bearing and Steering knuckle both side | H17: 2 | I17: 2 | J17: 4 | K17: Automobile||Lubricating Front Wheel Hub Bearing and Steering knuckle both side
A18: 17 | B18: Light | C18: Automobile | D18: Automobile | E18: II. General Service B = 10,000 KM | F18: Preventive | G18: Lubricating Rear Wheel Hub Bearing both side | H18: 1 | I18: 2 | J18: 2 | K18: Automobile||Lubricating Rear Wheel Hub Bearing both side
A19: 18 | B19: Light | C19: Automobile | D19: Automobile | E19: II. General Service B = 10,000 KM | F19: Preventive | G19: Inspection of fuel lines & Connection | H19: 1 | I19: 1 | J19: 1 | K19: Automobile||Inspection of fuel lines & Connection
A20: 19 | B20: Light | C20: Automobile | D20: Automobile | E20: III. General Service C = 20,000 KM | F20: Preventive | G20: Perform all activities in General Service "B" | H20: 24.5 | I20: - | J20: 36.5 | K20: Automobile||Perform all activities in General Service "B"
A21: 20 | B21: Light | C21: Automobile | D21: Automobile | E21: III. General Service C = 20,000 KM | F21: Preventive | G21: Change all Gear oil (Transmission Oil & Differential oil) | H21: 2 | I21: 1 | J21: 2 | K21: Automobile||Change all Gear oil (Transmission Oil & Differential oil)
A22: 21 | B22: Light | C22: Automobile | D22: Automobile | E22: III. General Service C = 20,000 KM | F22: Preventive | G22: Change Spark plugs | H22: 1 | I22: 1 | J22: 1 | K22: Automobile||Change Spark plugs
A23: 22 | B23: Light | C23: Automobile | D23: Automobile | E23: III. General Service C = 20,000 KM | F23: Preventive | G23: Change contact points | H23: 1 | I23: 1 | J23: 1 | K23: Automobile||Change contact points
A24: 23 | B24: Light | C24: Automobile | D24: Automobile | E24: III. General Service C = 20,000 KM | F24: Preventive | G24: Check and tightening bolts & nuts on Chassis & Body | H24: 2 | I24: 1 | J24: 2 | K24: Automobile||Check and tightening bolts & nuts on Chassis & Body
A25: 24 | B25: Light | C25: Automobile | D25: Automobile | E25: III. General Service C = 20,000 KM | F25: Preventive | G25: Cleaning and adjusting all brakes | H25: 2 | I25: 2 | J25: 4 | K25: Automobile||Cleaning and adjusting all brakes
A26: 25 | B26: Light | C26: Automobile | D26: Automobile | E26: IV. General Service C = 40,000 KM | F26: Preventive | G26: Perform all activities in General Service "C" | H26: 32.5 | I26: - | J26: 46.5 | K26: Automobile||Perform all activities in General Service "C"
A27: 26 | B27: Light | C27: Automobile | D27: Automobile | E27: IV. General Service C = 40,000 KM | F27: Preventive | G27: Change Clutch | H27: 4 | I27: 2 | J27: 8 | K27: Automobile||Change Clutch
A28: 27 | B28: Light | C28: Automobile | D28: Automobile | E28: IV. General Service C = 40,000 KM | F28: Preventive | G28: Changing Front Pad Kit | H28: 1 | I28: 1 | J28: 1 | K28: Automobile||Changing Front Pad Kit
A29: 28 | B29: Light | C29: Automobile | D29: Automobile | E29: IV. General Service C = 40,000 KM | F29: Preventive | G29: Change Rear Brake Pad kit/ Shoe kit | H29: 1.5 | I29: 1 | J29: 1.5 | K29: Automobile||Change Rear Brake Pad kit/ Shoe kit
A30: 29 | B30: Light | C30: Automobile | D30: Automobile | E30: IV. General Service C = 40,000 KM | F30: Preventive | G30: Check and Adjust engine Intake and Exhaust Valves | H30: 2 | I30: 2 | J30: 4 | K30: Automobile||Check and Adjust engine Intake and Exhaust Valves
A31: 30 | B31: Light | C31: Automobile | D31: Automobile | E31: IV. General Service C = 40,000 KM | F31: Preventive | G31: Check & adjust Front wheel toe in and toe out | H31: 2 | I31: 2 | J31: 4 | K31: Automobile||Check & adjust Front wheel toe in and toe out
A32: 31 | B32: Light | C32: Automobile | D32: Automobile | E32: IV. General Service C = 40,000 KM | F32: Preventive | G32: Check Serviceable Battery Electrolyte | H32: 1 | I32: 1 | J32: 1 | K32: Automobile||Check Serviceable Battery Electrolyte
A33: 32 | B33: Light | C33: Automobile | D33: Automobile | E33: V. Overhaul | F33: Overhaul | G33: Dismounting Engine | H33: 6 | I33: 2 | J33: 12 | K33: Automobile||Dismounting Engine
A34: 33 | B34: Light | C34: Automobile | D34: Automobile | E34: V. Overhaul | F34: Overhaul | G34: Engine Overhaul | H34: 52 | I34: 2 | J34: 104 | K34: Automobile||Engine Overhaul
A35: 34 | B35: Light | C35: Automobile | D35: Automobile | E35: V. Overhaul | F35: Overhaul | G35: Mounting & Test Engine | H35: 12 | I35: 2 | J35: 24 | K35: Automobile||Mounting & Test Engine
A36: 35 | B36: Light | C36: Automobile | D36: Automobile | E36: V. Overhaul | F36: Overhaul | G36: Overhaul Gear box | H36: 18 | I36: 2 | J36: 36 | K36: Automobile||Overhaul Gear box
A37: 36 | B37: Light | C37: Automobile | D37: Automobile | E37: V. Overhaul | F37: Overhaul | G37: Overhaul Differential rear | H37: 9 | I37: 2 | J37: 18 | K37: Automobile||Overhaul Differential rear
A38: 37 | B38: Light | C38: Automobile | D38: Automobile | E38: V. Overhaul | F38: Overhaul | G38: Overhaul Steering box /Power | H38: 12 | I38: 2 | J38: 24 | K38: Automobile||Overhaul Steering box /Power
... A179: 178 | B179: Light | C179: Pick Up / Station Wagon / Mini Bus | D179: Pick_Up_Station_Wagon_Mini_Bus | E179: I. General Service A = 5,000 KM | F179: Preventive | G179: Check Function of all lights | H179: 1 | I179: 2 | J179: 2 | K179: Pick Up / Station Wagon / Mini Bus||Check Function of all lights
A180: 179 | B180: Light | C180: Pick Up / Station Wagon / Mini Bus | D180: Pick_Up_Station_Wagon_Mini_Bus | E180: II. General Service B = 10,000 KM | F180: Preventive | G180: Perform all activities in General Service "A" | H180: 21.5 | I180: - | J180: 33.5 | K180: Pick Up / Station Wagon / Mini Bus||Perform all activities in General Service "A"
A181: 180 | B181: Light | C181: Pick Up / Station Wagon / Mini Bus | D181: Pick_Up_Station_Wagon_Mini_Bus | E181: II. General Service B = 10,000 KM | F181: Preventive | G181: Change Fuel filter | H181: 1 | I181: 1 | J181: 1 | K181: Pick Up / Station Wagon / Mini Bus||Change Fuel filter
A182: 181 | B182: Light | C182: Pick Up / Station Wagon / Mini Bus | D182: Pick_Up_Station_Wagon_Mini_Bus | E182: II. General Service B = 10,000 KM | F182: Preventive | G182: Check the condition & Security of seat | H182: 1 | I182: 2 | J182: 2 | K182: Pick Up / Station Wagon / Mini Bus||Check the condition & Security of seat
A183: 182 | B183: Light | C183: Pick Up / Station Wagon / Mini Bus | D183: Pick_Up_Station_Wagon_Mini_Bus | E183: II. General Service B = 10,000 KM | F183: Preventive | G183: Check all suspension, Shock absorbers, Stabilizer Bushings & Arm Bushings | H183: 2.5 | I183: 2 | J183: 5 | K183: Pick Up / Station Wagon / Mini Bus||Check all suspension, Shock absorbers, Stabilizer Bushings & Arm Bushings
A184: 183 | B184: Light | C184: Pick Up / Station Wagon / Mini Bus | D184: Pick_Up_Station_Wagon_Mini_Bus | E184: II. General Service B = 10,000 KM | F184: Preventive | G184: Check and top up all gear oil | H184: 2 | I184: 1 | J184: 2 | K184: Pick Up / Station Wagon / Mini Bus||Check and top up all gear oil
A185: 184 | B185: Light | C185: Pick Up / Station Wagon / Mini Bus | D185: Pick_Up_Station_Wagon_Mini_Bus | E185: II. General Service B = 10,000 KM | F185: Preventive | G185: Clean battery terminals | H185: 0.5 | I185: 1 | J185: 0.5 | K185: Pick Up / Station Wagon / Mini Bus||Clean battery terminals
A186: 185 | B186: Light | C186: Pick Up / Station Wagon / Mini Bus | D186: Pick_Up_Station_Wagon_Mini_Bus | E186: II. General Service B = 10,000 KM | F186: Preventive | G186: Check Exhaust system for leakage & Damage | H186: 1 | I186: 1 | J186: 1 | K186: Pick Up / Station Wagon / Mini Bus||Check Exhaust system for leakage & Damage
A187: 186 | B187: Light | C187: Pick Up / Station Wagon / Mini Bus | D187: Pick_Up_Station_Wagon_Mini_Bus | E187: II. General Service B = 10,000 KM | F187: Preventive | G187: Changing Air Cleaner | H187: 0.5 | I187: 1 | J187: 0.5 | K187: Pick Up / Station Wagon / Mini Bus||Changing Air Cleaner
A188: 187 | B188: Light | C188: Pick Up / Station Wagon / Mini Bus | D188: Pick_Up_Station_Wagon_Mini_Bus | E188: III. General Service C = 20,000 KM | F188: Preventive | G188: Perform all activities in General Service "B" | H188: 30 | I188: - | J188: 45.5 | K188: Pick Up / Station Wagon / Mini Bus||Perform all activities in General Service "B"
A189: 188 | B189: Light | C189: Pick Up / Station Wagon / Mini Bus | D189: Pick_Up_Station_Wagon_Mini_Bus | E189: III. General Service C = 20,000 KM | F189: Preventive | G189: Renew Hub Grease front and rear wheels | H189: 8 | I189: 2 | J189: 16 | K189: Pick Up / Station Wagon / Mini Bus||Renew Hub Grease front and rear wheels
A190: 189 | B190: Light | C190: Pick Up / Station Wagon / Mini Bus | D190: Pick_Up_Station_Wagon_Mini_Bus | E190: III. General Service C = 20,000 KM | F190: Preventive | G190: Change all Gear oil (Transmission Oil & Differential oil) | H190: 3 | I190: 1 | J190: 3 | K190: Pick Up / Station Wagon / Mini Bus||Change all Gear oil (Transmission Oil & Differential oil)
A191: 190 | B191: Light | C191: Pick Up / Station Wagon / Mini Bus | D191: Pick_Up_Station_Wagon_Mini_Bus | E191: III. General Service C = 20,000 KM | F191: Preventive | G191: Change Spark plugs | H191: 1 | I191: 1 | J191: 1 | K191: Pick Up / Station Wagon / Mini Bus||Change Spark plugs
A192: 191 | B192: Light | C192: Pick Up / Station Wagon / Mini Bus | D192: Pick_Up_Station_Wagon_Mini_Bus | E192: III. General Service C = 20,000 KM | F192: Preventive | G192: Change contact points | H192: 1 | I192: 1 | J192: 1 | K192: Pick Up / Station Wagon / Mini Bus||Change contact points
A193: 192 | B193: Light | C193: Pick Up / Station Wagon / Mini Bus | D193: Pick_Up_Station_Wagon_Mini_Bus | E193: III. General Service C = 20,000 KM | F193: Preventive | G193: Check and tightening bolts & nuts on Chassis & Body | H193: 4 | I193: 1 | J193: 4 | K193: Pick Up / Station Wagon / Mini Bus||Check and tightening bolts & nuts on Chassis & Body
A194: 193 | B194: Light | C194: Pick Up / Station Wagon / Mini Bus | D194: Pick_Up_Station_Wagon_Mini_Bus | E194: III. General Service C = 20,000 KM | F194: Preventive | G194: Cleaning and adjusting all brakes | H194: 4 | I194: 2 | J194: 8 | K194: Pick Up / Station Wagon / Mini Bus||Cleaning and adjusting all brakes
A195: 194 | B195: Light | C195: Pick Up / Station Wagon / Mini Bus | D195: Pick_Up_Station_Wagon_Mini_Bus | E195: IV. General Service C = 40,000 KM | F195: Preventive | G195: Perform all activities in General Service "C" | H195: 51 | I195: - | J195: 78.5 | K195: Pick Up / Station Wagon / Mini Bus||Perform all activities in General Service "C"
A196: 195 | B196: Light | C196: Pick Up / Station Wagon / Mini Bus | D196: Pick_Up_Station_Wagon_Mini_Bus | E196: IV. General Service C = 40,000 KM | F196: Preventive | G196: Changing all Brake, Clutch & Power steering fluid | H196: 4 | I196: 2 | J196: 8 | K196: Pick Up / Station Wagon / Mini Bus||Changing all Brake, Clutch & Power steering fluid
A197: 196 | B197: Light | C197: Pick Up / Station Wagon / Mini Bus | D197: Pick_Up_Station_Wagon_Mini_Bus | E197: IV. General Service C = 40,000 KM | F197: Preventive | G197: Changing Front Pad Kit | H197: 1 | I197: 1 | J197: 1 | K197: Pick Up / Station Wagon / Mini Bus||Changing Front Pad Kit
A198: 197 | B198: Light | C198: Pick Up / Station Wagon / Mini Bus | D198: Pick_Up_Station_Wagon_Mini_Bus | E198: IV. General Service C = 40,000 KM | F198: Preventive | G198: Change Rear Brake Pad kit | H198: 1 | I198: 1 | J198: 1 | K198: Pick Up / Station Wagon / Mini Bus||Change Rear Brake Pad kit
A199: 198 | B199: Light | C199: Pick Up / Station Wagon / Mini Bus | D199: Pick_Up_Station_Wagon_Mini_Bus | E199: IV. General Service C = 40,000 KM | F199: Preventive | G199: Change Rear brake shoe set | H199: 3 | I199: 2 | J199: 6 | K199: Pick Up / Station Wagon / Mini Bus||Change Rear brake shoe set
A200: 199 | B200: Light | C200: Pick Up / Station Wagon / Mini Bus | D200: Pick_Up_Station_Wagon_Mini_Bus | E200: IV. General Service C = 40,000 KM | F200: Preventive | G200: Check and Adjust engine Intake and Exhaust Valves | H200: 4 | I200: 2 | J200: 8 | K200: Pick Up / Station Wagon / Mini Bus||Check and Adjust engine Intake and Exhaust Valves
A201: 200 | B201: Light | C201: Pick Up / Station Wagon / Mini Bus | D201: Pick_Up_Station_Wagon_Mini_Bus | E201: IV. General Service C = 40,000 KM | F201: Preventive | G201: Check the performance of Clutch | H201: 1 | I201: 1 | J201: 1 | K201: Pick Up / Station Wagon / Mini Bus||Check the performance of Clutch
A202: 201 | B202: Light | C202: Pick Up / Station Wagon / Mini Bus | D202: Pick_Up_Station_Wagon_Mini_Bus | E202: IV. General Service C = 40,000 KM | F202: Preventive | G202: Check & adjust Front wheel toe in and toe out | H202: 2 | I202: 2 | J202: 4 | K202: Pick Up / Station Wagon / Mini Bus||Check & adjust Front wheel toe in and toe out
A203: 202 | B203: Light | C203: Pick Up / Station Wagon / Mini Bus | D203: Pick_Up_Station_Wagon_Mini_Bus | E203: IV. General Service C = 40,000 KM | F203: Preventive | G203: Check Serviceable Battery Electrolyte and Terminals | H203: 1 | I203: 1 | J203: 1 | K203: Pick Up / Station Wagon / Mini Bus||Check Serviceable Battery Electrolyte and Terminals
A204: 203 | B204: Light | C204: Pick Up / Station Wagon / Mini Bus | D204: Pick_Up_Station_Wagon_Mini_Bus | E204: V. Overhaul | F204: Overhaul | G204: Engine Tune-Up | H204: 8 | I204: 2 | J204: 16 | K204: Pick Up / Station Wagon / Mini Bus||Engine Tune-Up
A205: 204 | B205: Light | C205: Pick Up / Station Wagon / Mini Bus | D205: Pick_Up_Station_Wagon_Mini_Bus | E205: V. Overhaul | F205: Overhaul | G205: Engine Overhaul | H205: 66 | I205: 2 | J205: 132 | K205: Pick Up / Station Wagon / Mini Bus||Engine Overhaul
A206: 205 | B206: Light | C206: Pick Up / Station Wagon / Mini Bus | D206: Pick_Up_Station_Wagon_Mini_Bus | E206: V. Overhaul | F206: Overhaul | G206: Overhaul Engine Top | H206: 24 | I206: 2 | J206: 48 | K206: Pick Up / Station Wagon / Mini Bus||Overhaul Engine Top
A207: 206 | B207: Light | C207: Pick Up / Station Wagon / Mini Bus | D207: Pick_Up_Station_Wagon_Mini_Bus | E207: V. Overhaul | F207: Overhaul | G207: Overhaul Engine Bottom | H207: 18 | I207: 2 | J207: 36 | K207: Pick Up / Station Wagon / Mini Bus||Overhaul Engine Bottom
... A365: 364 | B365: Heavy | C365: Heavy Truck | D365: Heavy_Truck | E365: I. General Service A = 5,000 KM | F365: Preventive | G365: Inspection of Mechanical & Electrical Parts and all Fluids top Upping & Greasing | H365: 12 | I365: 3 | J365: 36 | K365: Heavy Truck||Inspection of Mechanical & Electrical Parts and all Fluids top Upping & Greasing
A366: 365 | B366: Heavy | C366: Heavy Truck | D366: Heavy_Truck | E366: II. General Service B = 10,000 KM | F366: Preventive | G366: Perform all activities in General Service "A" | H366: 13.5 | I366: - | J366: 39 | K366: Heavy Truck||Perform all activities in General Service "A"
A367: 366 | B367: Heavy | C367: Heavy Truck | D367: Heavy_Truck | E367: II. General Service B = 10,000 KM | F367: Preventive | G367: Change Fuel filter | H367: 3 | I367: 2 | J367: 6 | K367: Heavy Truck||Change Fuel filter
A368: 367 | B368: Heavy | C368: Heavy Truck | D368: Heavy_Truck | E368: II. General Service B = 10,000 KM | F368: Preventive | G368: Check the condition & Security of seat | H368: 1 | I368: 1 | J368: 1 | K368: Heavy Truck||Check the condition & Security of seat
A369: 368 | B369: Heavy | C369: Heavy Truck | D369: Heavy_Truck | E369: II. General Service B = 10,000 KM | F369: Preventive | G369: Lubricating Front Wheel Hub Bearing and Steering knuckle both side | H369: 6 | I369: 2 | J369: 12 | K369: Heavy Truck||Lubricating Front Wheel Hub Bearing and Steering knuckle both side
A370: 369 | B370: Heavy | C370: Heavy Truck | D370: Heavy_Truck | E370: II. General Service B = 10,000 KM | F370: Preventive | G370: Servicing Front & rear Brakes, Hoses, Lines and Hand Brakes | H370: 18 | I370: 2 | J370: 36 | K370: Heavy Truck||Servicing Front & rear Brakes, Hoses, Lines and Hand Brakes
A371: 370 | B371: Heavy | C371: Heavy Truck | D371: Heavy_Truck | E371: II. General Service B = 10,000 KM | F371: Preventive | G371: Changing Air Cleaner | H371: 0.5 | I371: 1 | J371: 0.5 | K371: Heavy Truck||Changing Air Cleaner
A372: 371 | B372: Heavy | C372: Heavy Truck | D372: Heavy_Truck | E372: III. General Service C = 20,000 KM | F372: Preventive | G372: Perform all activities in General Service "B" | H372: 42 | I372: - | J372: 94.5 | K372: Heavy Truck||Perform all activities in General Service "B"
A373: 372 | B373: Heavy | C373: Heavy Truck | D373: Heavy_Truck | E373: III. General Service C = 20,000 KM | F373: Preventive | G373: Renew Hub Grease Single wheels | H373: 3 | I373: 2 | J373: 6 | K373: Heavy Truck||Renew Hub Grease Single wheels
A374: 373 | B374: Heavy | C374: Heavy Truck | D374: Heavy_Truck | E374: III. General Service C = 20,000 KM | F374: Preventive | G374: Change all Gear oil (Transmission Oil & Differential oil) | H374: 3 | I374: 2 | J374: 6 | K374: Heavy Truck||Change all Gear oil (Transmission Oil & Differential oil)
A375: 374 | B375: Heavy | C375: Heavy Truck | D375: Heavy_Truck | E375: III. General Service C = 20,000 KM | F375: Preventive | G375: Servicing of relay end & tie rod ends and steering gear box, Steering Damper | H375: 18 | I375: 3 | J375: 54 | K375: Heavy Truck||Servicing of relay end & tie rod ends and steering gear box, Steering Damper
A376: 375 | B376: Heavy | C376: Heavy Truck | D376: Heavy_Truck | E376: III. General Service C = 20,000 KM | F376: Preventive | G376: Replacing of belts and Hoses | H376: 2 | I376: 1 | J376: 2 | K376: Heavy Truck||Replacing of belts and Hoses
A377: 376 | B377: Heavy | C377: Heavy Truck | D377: Heavy_Truck | E377: III. General Service C = 20,000 KM | F377: Preventive | G377: Adjust Valve Clearance Screw Type | H377: 6 | I377: 2 | J377: 12 | K377: Heavy Truck||Adjust Valve Clearance Screw Type
A378: 377 | B378: Heavy | C378: Heavy Truck | D378: Heavy_Truck | E378: III. General Service C = 20,000 KM | F378: Preventive | G378: Check and tightening bolts & nuts on Chassis & Body | H378: 6 | I378: 2 | J378: 12 | K378: Heavy Truck||Check and tightening bolts & nuts on Chassis & Body
A379: 378 | B379: Heavy | C379: Heavy Truck | D379: Heavy_Truck | E379: IV. General Service D = 40,000 KM | F379: Preventive | G379: Perform all activities in General Service "C" | H379: 80 | I379: - | J379: 186.5 | K379: Heavy Truck||Perform all activities in General Service "C"
A380: 379 | B380: Heavy | C380: Heavy Truck | D380: Heavy_Truck | E380: IV. General Service D = 40,000 KM | F380: Preventive | G380: Replace Shock absorbers, Stabilizer Bushings & Arm Bushings if necessary | H380: 9 | I380: 2 | J380: 18 | K380: Heavy Truck||Replace Shock absorbers, Stabilizer Bushings & Arm Bushings if necessary
A381: 380 | B381: Heavy | C381: Heavy Truck | D381: Heavy_Truck | E381: IV. General Service D = 40,000 KM | F381: Preventive | G381: Changing Clutch & Power steering fluid | H381: 3 | I381: 2 | J381: 6 | K381: Heavy Truck||Changing Clutch & Power steering fluid
A382: 381 | B382: Heavy | C382: Heavy Truck | D382: Heavy_Truck | E382: IV. General Service D = 40,000 KM | F382: Preventive | G382: Change brake shoe set /Single/ | H382: 3 | I382: 2 | J382: 6 | K382: Heavy Truck||Change brake shoe set /Single/
A383: 382 | B383: Heavy | C383: Heavy Truck | D383: Heavy_Truck | E383: IV. General Service D = 40,000 KM | F383: Preventive | G383: Check and Adjust engine Intake and Exhaust Valves | H383: 6 | I383: 2 | J383: 12 | K383: Heavy Truck||Check and Adjust engine Intake and Exhaust Valves
A384: 383 | B384: Heavy | C384: Heavy Truck | D384: Heavy_Truck | E384: IV. General Service D = 40,000 KM | F384: Preventive | G384: Check & adjust Front wheel toe in and toe out | H384: 3 | I384: 2 | J384: 6 | K384: Heavy Truck||Check & adjust Front wheel toe in and toe out
A385: 384 | B385: Heavy | C385: Heavy Truck | D385: Heavy_Truck | E385: V. Engine Repair | F385: Corrective | G385: Engine Tune-Up | H385: 8 | I385: 2 | J385: 16 | K385: Heavy Truck||Engine Tune-Up
A386: 385 | B386: Heavy | C386: Heavy Truck | D386: Heavy_Truck | E386: V. Engine Repair | F386: Corrective | G386: Dismounting Engine | H386: 12 | I386: 3 | J386: 36 | K386: Heavy Truck||Dismounting Engine
A387: 386 | B387: Heavy | C387: Heavy Truck | D387: Heavy_Truck | E387: V. Engine Repair | F387: Corrective | G387: Wash & Clean Engine Parts | H387: 2 | I387: 2 | J387: 4 | K387: Heavy Truck||Wash & Clean Engine Parts
A388: 387 | B388: Heavy | C388: Heavy Truck | D388: Heavy_Truck | E388: V. Engine Repair | F388: Corrective | G388: Engine Top Overhaul | H388: 36 | I388: 3 | J388: 108 | K388: Heavy Truck||Engine Top Overhaul
A389: 388 | B389: Heavy | C389: Heavy Truck | D389: Heavy_Truck | E389: V. Engine Repair | F389: Corrective | G389: Engine Overhaul | H389: 102 | I389: 3 | J389: 306 | K389: Heavy Truck||Engine Overhaul
A390: 389 | B390: Heavy | C390: Heavy Truck | D390: Heavy_Truck | E390: V. Engine Repair | F390: Corrective | G390: Repair Turbo charger | H390: 8 | I390: 2 | J390: 16 | K390: Heavy Truck||Repair Turbo charger
A391: 390 | B391: Heavy | C391: Heavy Truck | D391: Heavy_Truck | E391: V. Engine Repair | F391: Corrective | G391: Mounting and Test Engine | H391: 18 | I391: 3 | J391: 54 | K391: Heavy Truck||Mounting and Test Engine
... A529: 528 | B529: Machinery | C529: Earth Moving Machinery (General PM & Engine) | D529: Earth_Moving_Machinery_General_PM_Engine | E529: II. Every 250 Service Hours or Monthly | F529: Preventive | G529: Grease Service | H529: 2 | I529: 1 | J529: 2 | K529: Earth Moving Machinery (General PM & Engine)||Grease Service
A530: 529 | B530: Machinery | C530: Earth Moving Machinery (General PM & Engine) | D530: Earth_Moving_Machinery_General_PM_Engine | E530: III. Every 500 Service Hours or 3 months | F530: Preventive | G530: Perform all activities of 250 hr. service | H530: 12 | I530: - | J530: 16 | K530: Earth Moving Machinery (General PM & Engine)||Perform all activities of 250 hr. service
A531: 530 | B531: Machinery | C531: Earth Moving Machinery (General PM & Engine) | D531: Earth_Moving_Machinery_General_PM_Engine | E531: III. Every 500 Service Hours or 3 months | F531: Preventive | G531: Check Cooling System or Coolant | H531: 2 | I531: 1 | J531: 2 | K531: Earth Moving Machinery (General PM & Engine)||Check Cooling System or Coolant
A532: 531 | B532: Machinery | C532: Earth Moving Machinery (General PM & Engine) | D532: Earth_Moving_Machinery_General_PM_Engine | E532: III. Every 500 Service Hours or 3 months | F532: Preventive | G532: Check Hydraulic System Oil level and Transmission Oil level | H532: 1 | I532: 1 | J532: 1 | K532: Earth Moving Machinery (General PM & Engine)||Check Hydraulic System Oil level and Transmission Oil level
A533: 532 | B533: Machinery | C533: Earth Moving Machinery (General PM & Engine) | D533: Earth_Moving_Machinery_General_PM_Engine | E533: III. Every 500 Service Hours or 3 months | F533: Preventive | G533: Replace Fuel System Primary & secondary Filter or Water Separator | H533: 3 | I533: 1 | J533: 3 | K533: Earth Moving Machinery (General PM & Engine)||Replace Fuel System Primary & secondary Filter or Water Separator
A534: 533 | B534: Machinery | C534: Earth Moving Machinery (General PM & Engine) | D534: Earth_Moving_Machinery_General_PM_Engine | E534: III. Every 500 Service Hours or 3 months | F534: Preventive | G534: Clean Fuel Tank Cap and Strainer | H534: 1 | I534: 1 | J534: 1 | K534: Earth Moving Machinery (General PM & Engine)||Clean Fuel Tank Cap and Strainer
...

Sheet Asset Register
A1: Asset ID | B1: Asset / Equipment Name | C1: Category | D1: Equipment Type | E1: Make | F1: Manufacturing Year | G1: Fuel Norm (L/hr) | H1: Lease Rate/Hour (ETB) | I1: Status
A2: AA-65266 | B2: Bull Dozer (CAT) | C2: Machinery | D2: Dozer | E2: CAT | F2: 2018 | G2: 28 | H2: 1800 | I2: Active
A3: AA-65265 | B3: Bull Dozer (CAT) | C3: Machinery | D3: Dozer | E3: CAT | F3: 2015 | G3: 28 | H3: 1800 | I3: Down
A4: AA-60042 | B4: Bull Dozer (Komatsu) | C4: Machinery | D4: Dozer | E4: Komatsu | F4: 2019 | G4: 28 | H4: 1800 | I4: Active
A5: AA-65585 | B5: Dump Truck (Volvo) | C5: Heavy | D5: Heavy Truck | E5: Volvo | F5: 2020 | G5: 24 | H5: 1500 | I5: Active
A6: AA-9018 | B6: Bull Dozer (CAT) | C6: Machinery | D6: Dozer | E6: CAT | F6: 2014 | G6: 26 | H6: 1800 | I6: Active
A7: LV-1001 | B7: Toyota Land Cruiser | C7: Light | D7: Automobile | E7: Toyota | F7: 2022 | G7: 12 | H7: 450 | I7: Active
A8: LV-1002 | B8: Toyota Hilux Pickup | C8: Light | D8: Pick Up / Station Wagon / Mini Bus | E8: Toyota | F8: 2021 | G8: 9 | H8: 400 | I8: Active
A9: LV-1003 | B9: Sedan Pool Car | C9: Light | D9: Automobile | E9: Toyota | F9: 2020 | G9: 7 | H9: 350 | I9: Active
A10: EX-2001 | B10: Excavator (Komatsu PC200) | C10: Machinery | D10: Excavator | E10: Komatsu | F10: 2019 | G10: 22 | H10: 2200 | I10: Active
A11: GD-3001 | B11: Grader (CAT 140K) | C11: Machinery | D11: Grader | E11: CAT | F11: 2017 | G11: 20 | H11: 2000 | I11: Active
A12: LD-4001 | B12: Wheel Loader (CAT 950) | C12: Machinery | D12: Loader | E12: CAT | F12: 2018 | G12: 18 | H12: 1900 | I12: Active
A13: GN-5001 | B13: Standby Generator 150KVA | C13: Others | D13: Generator | E13: Perkins | F13: 2016 | G13: 12 | H13: 300 | I13: Active
... A15: HT-7001 | B15: Heavy Fuel Tanker | C15: Heavy | D15: Heavy Truck | E15: Isuzu | F15: 2017 | G15: 30 | H15: 1600 | I15: Active
A16: EL-8001 | B16: Site Electrical Panel | C16: Others | D16: Electrical & Electronics | E16: - | F16: 2015 | H16: 200 | I16: Active

Sheet Lists
A1: Category | B1: Light | C1: Heavy | D1: Machinery | E1: Others | G1: MType
A2: Light | B2: Automobile | C2: Heavy Truck | D2: Earth Moving Machinery (General PM & Engine) | E2: Generator | G2: Preventive
A3: Heavy | B3: Pick Up / Station Wagon / Mini Bus | D3: Dozer | E3: Air Compressor | G3: Corrective
A4: Machinery | D4: Excavator | E4: Electrical & Electronics | G4: Overhaul
A5: Others | D5: Loader
D6: Grader

Sheet Daily Operations Log
A1: Log ID | B1: Date | C1: Asset ID | D1: Asset Name | E1: Category | F1: Equipment Type | G1: Operable Hr | H1: Idle Hr | I1: Down Hr | J1: Availability % | K1: Utilization % | L1: Down % | M1: Reason for Down | N1: Reason for Idle | O1: Fuel Norm (L/hr) | P1: Actual Fuel (L) | Q1: Expected Fuel (L) | R1: Fuel Variance (L) | S1: Fuel Variance % | T1: Lease Rate/Hour (ETB) | U1: Total Revenue (ETB) | V1: Idle % (of Operable)
A2: =IF(B2="","",ROW()-1) -> 1 | B2: 2026-07-06 | C2: AA-65266 | D2: =IFERROR(INDEX('Asset Register'!$B:$B,MATCH($C2,'Asset Register'!$A:$A,0)),"") -> Bull Dozer (CAT) | E2: =IFERROR(INDEX('Asset Register'!$C:$C,MATCH($C2,'Asset Register'!$A:$A,0)),"") -> Machinery | F2: =IFERROR(INDEX('Asset Register'!$D:$D,MATCH($C2,'Asset Register'!$A:$A,0)),"") -> Dozer | G2: 5.5 | H2: 2 | I2: 0.5 | J2: =IFERROR($G2/($G2+$I2),"") -> 0.91666667 | K2: =IFERROR($G2/($G2+$H2+$I2),"") -> 0.6875 | L2: =IF($J2="","",1-$J2) -> 0.083333333 | O2: =IFERROR(INDEX('Asset Register'!$G:$G,MATCH($C2,'Asset Register'!$A:$A,0)),"") -> 28 | P2: 154 | Q2: =IF($O2="","",$O2*$G2) -> 154 | R2: =IF(OR($P2="",$Q2=""),"",$P2-$Q2) -> 0 | S2: =IF(OR($R2="",$Q2="",$Q2=0),"",$R2/$Q2) -> 0 | T2: =IFERROR(INDEX('Asset Register'!$H:$H,MATCH($C2,'Asset Register'!$A:$A,0)),"") -> 1800 | U2: =IF($T2="","",$G2*$T2) -> 9900 | V2: =IFERROR($H2/$G2,"") -> 0.36363636
A3: =IF(B3="","",ROW()-1) -> 2 | B3: 2026-07-06 | C3: AA-65265 | D3: =IFERROR(INDEX('Asset Register'!$B:$B,MATCH($C3,'Asset Register'!$A:$A,0)),"") -> Bull Dozer (CAT) | E3: =IFERROR(INDEX('Asset Register'!$C:$C,MATCH($C3,'Asset Register'!$A:$A,0)),"") -> Machinery | F3: =IFERROR(INDEX('Asset Register'!$D:$D,MATCH($C3,'Asset Register'!$A:$A,0)),"") -> Dozer | G3: 0 | H3: 0 | I3: 8 | J3: =IFERROR($G3/($G3+$I3),"") -> 0 | K3: =IFERROR($G3/($G3+$H3+$I3),"") -> 0 | L3: =IF($J3="","",1-$J3) -> 1 | M3: Under Carriage Damage (since 2026-06-12) - awaiting parts | O3: =IFERROR(INDEX('Asset Register'!$G:$G,MATCH($C3,'Asset Register'!$A:$A,0)),"") -> 28 | P3: 0 | Q3: =IF($O3="","",$O3*$G3) -> 0 | R3: =IF(OR($P3="",$Q3=""),"",$P3-$Q3) -> 0 | S3: =IF(OR($R3="",$Q3="",$Q3=0),"",$R3/$Q3) | T3: =IFERROR(INDEX('Asset Register'!$H:$H,MATCH($C3,'Asset Register'!$A:$A,0)),"") -> 1800 | U3: =IF($T3="","",$G3*$T3) -> 0 | V3: =IFERROR($H3/$G3,"")
A4: =IF(B4="","",ROW()-1) -> 3 | B4: 2026-07-06 | C4: AA-60042 | D4: =IFERROR(INDEX('Asset Register'!$B:$B,MATCH($C4,'Asset Register'!$A:$A,0)),"") -> Bull Dozer (Komatsu) | E4: =IFERROR(INDEX('Asset Register'!$C:$C,MATCH($C4,'Asset Register'!$A:$A,0)),"") -> Machinery | F4: =IFERROR(INDEX('Asset Register'!$D:$D,MATCH($C4,'Asset Register'!$A:$A,0)),"") -> Dozer | G4: 4 | H4: 4 | I4: 0 | J4: =IFERROR($G4/($G4+$I4),"") -> 1 | K4: =IFERROR($G4/($G4+$H4+$I4),"") -> 0.5 | L4: =IF($J4="","",1-$J4) -> 0 | O4: =IFERROR(INDEX('Asset Register'!$G:$G,MATCH($C4,'Asset Register'!$A:$A,0)),"") -> 28 | P4: 120 | Q4: =IF($O4="","",$O4*$G4) -> 112 | R4: =IF(OR($P4="",$Q4=""),"",$P4-$Q4) -> 8 | S4: =IF(OR($R4="",$Q4="",$Q4=0),"",$R4/$Q4) -> 0.071428571 | T4: =IFERROR(INDEX('Asset Register'!$H:$H,MATCH($C4,'Asset Register'!$A:$A,0)),"") -> 1800 | U4: =IF($T4="","",$G4*$T4) -> 7200 | V4: =IFERROR($H4/$G4,"") -> 1
A5: =IF(B5="","",ROW()-1) -> 4 | B5: 2026-07-06 | C5: AA-65585 | D5: =IFERROR(INDEX('Asset Register'!$B:$B,MATCH($C5,'Asset Register'!$A:$A,0)),"") -> Dump Truck (Volvo) | E5: =IFERROR(INDEX('Asset Register'!$C:$C,MATCH($C5,'Asset Register'!$A:$A,0)),"") -> Heavy | F5: =IFERROR(INDEX('Asset Register'!$D:$D,MATCH($C5,'Asset Register'!$A:$A,0)),"") -> Heavy Truck | G5: 6.5 | H5: 1.5 | I5: 0 | J5: =IFERROR($G5/($G5+$I5),"") -> 1 | K5: =IFERROR($G5/($G5+$H5+$I5),"") -> 0.8125 | L5: =IF($J5="","",1-$J5) -> 0 | O5: =IFERROR(INDEX('Asset Register'!$G:$G,MATCH($C5,'Asset Register'!$A:$A,0)),"") -> 24 | P5: 182 | Q5: =IF($O5="","",$O5*$G5) -> 156 | R5: =IF(OR($P5="",$Q5=""),"",$P5-$Q5) -> 26 | S5: =IF(OR($R5="",$Q5="",$Q5=0),"",$R5/$Q5) -> 0.16666667 | T5: =IFERROR(INDEX('Asset Register'!$H:$H,MATCH($C5,'Asset Register'!$A:$A,0)),"") -> 1500 | U5: =IF($T5="","",$G5*$T5) -> 9750 | V5: =IFERROR($H5/$G5,"") -> 0.23076923
A6: =IF(B6="","",ROW()-1) -> 5 | B6: 2026-07-06 | C6: AA-9018 | D6: =IFERROR(INDEX('Asset Register'!$B:$B,MATCH($C6,'Asset Register'!$A:$A,0)),"") -> Bull Dozer (CAT) | E6: =IFERROR(INDEX('Asset Register'!$C:$C,MATCH($C6,'Asset Register'!$A:$A,0)),"") -> Machinery | F6: =IFERROR(INDEX('Asset Register'!$D:$D,MATCH($C6,'Asset Register'!$A:$A,0)),"") -> Dozer | G6: 5 | H6: 1 | I6: 2 | J6: =IFERROR($G6/($G6+$I6),"") -> 0.71428571 | K6: =IFERROR($G6/($G6+$H6+$I6),"") -> 0.625 | L6: =IF($J6="","",1-$J6) -> 0.28571429 | M6: ECM Electrical Fault (2026-07-05) | O6: =IFERROR(INDEX('Asset Register'!$G:$G,MATCH($C6,'Asset Register'!$A:$A,0)),"") -> 26 | P6: 140 | Q6: =IF($O6="","",$O6*$G6) -> 130 | R6: =IF(OR($P6="",$Q6=""),"",$P6-$Q6) -> 10 | S6: =IF(OR($R6="",$Q6="",$Q6=0),"",$R6/$Q6) -> 0.076923077 | T6: =IFERROR(INDEX('Asset Register'!$H:$H,MATCH($C6,'Asset Register'!$A:$A,0)),"") -> 1800 | U6: =IF($T6="","",$G6*$T6) -> 9000 | V6: =IFERROR($H6/$G6,"") -> 0.2
A7: =IF(B7="","",ROW()-1) -> 6 | B7: 2026-07-09 | C7: LV-1001 | D7: =IFERROR(INDEX('Asset Register'!$B:$B,MATCH($C7,'Asset Register'!$A:$A,0)),"") -> Toyota Land Cruiser | E7: =IFERROR(INDEX('Asset Register'!$C:$C,MATCH($C7,'Asset Register'!$A:$A,0)),"") -> Light | F7: =IFERROR(INDEX('Asset Register'!$D:$D,MATCH($C7,'Asset Register'!$A:$A,0)),"") -> Automobile | G7: 6 | H7: 1 | I7: 0 | J7: =IFERROR($G7/($G7+$I7),"") -> 1 | K7: =IFERROR($G7/($G7+$H7+$I7),"") -> 0.85714286 | L7: =IF($J7="","",1-$J7) -> 0 | O7: =IFERROR(INDEX('Asset Register'!$G:$G,MATCH($C7,'Asset Register'!$A:$A,0)),"") -> 12 | P7: 75 | Q7: =IF($O7="","",$O7*$G7) -> 72 | R7: =IF(OR($P7="",$Q7=""),"",$P7-$Q7) -> 3 | S7: =IF(OR($R7="",$Q7="",$Q7=0),"",$R7/$Q7) -> 0.041666667 | T7: =IFERROR(INDEX('Asset Register'!$H:$H,MATCH($C7,'Asset Register'!$A:$A,0)),"") -> 450 | U7: =IF($T7="","",$G7*$T7) -> 2700 | V7: =IFERROR($H7/$G7,"") -> 0.16666667
A8: =IF(B8="","",ROW()-1) -> 7 | B8: 2026-07-09 | C8: LV-1002 | D8: =IFERROR(INDEX('Asset Register'!$B:$B,MATCH($C8,'Asset Register'!$A:$A,0)),"") -> Toyota Hilux Pickup | E8: =IFERROR(INDEX('Asset Register'!$C:$C,MATCH($C8,'Asset Register'!$A:$A,0)),"") -> Light | F8: =IFERROR(INDEX('Asset Register'!$D:$D,MATCH($C8,'Asset Register'!$A:$A,0)),"") -> Pick Up / Station Wagon / Mini Bus | G8: 7 | H8: 0.5 | I8: 0 | J8: =IFERROR($G8/($G8+$I8),"") -> 1 | K8: =IFERROR($G8/($G8+$H8+$I8),"") -> 0.93333333 | L8: =IF($J8="","",1-$J8) -> 0 | O8: =IFERROR(INDEX('Asset Register'!$G:$G,MATCH($C8,'Asset Register'!$A:$A,0)),"") -> 9 | P8: 66 | Q8: =IF($O8="","",$O8*$G8) -> 63 | R8: =IF(OR($P8="",$Q8=""),"",$P8-$Q8) -> 3 | S8: =IF(OR($R8="",$Q8="",$Q8=0),"",$R8/$Q8) -> 0.047619048 | T8: =IFERROR(INDEX('Asset Register'!$H:$H,MATCH($C8,'Asset Register'!$A:$A,0)),"") -> 400 | U8: =IF($T8="","",$G8*$T8) -> 2800 | V8: =IFERROR($H8/$G8,"") -> 0.071428571
A9: =IF(B9="","",ROW()-1) -> 8 | B9: 2026-07-09 | C9: LV-1003 | D9: =IFERROR(INDEX('Asset Register'!$B:$B,MATCH($C9,'Asset Register'!$A:$A,0)),"") -> Sedan Pool Car | E9: =IFERROR(INDEX('Asset Register'!$C:$C,MATCH($C9,'Asset Register'!$A:$A,0)),"") -> Light | F9: =IFERROR(INDEX('Asset Register'!$D:$D,MATCH($C9,'Asset Register'!$A:$A,0)),"") -> Automobile | G9: 5 | H9: 1 | I9: 0 | J9: =IFERROR($G9/($G9+$I9),"") -> 1 | K9: =IFERROR($G9/($G9+$H9+$I9),"") -> 0.83333333 | L9: =IF($J9="","",1-$J9) -> 0 | O9: =IFERROR(INDEX('Asset Register'!$G:$G,MATCH($C9,'Asset Register'!$A:$A,0)),"") -> 7 | P9: 34 | Q9: =IF($O9="","",$O9*$G9) -> 35 | R9: =IF(OR($P9="",$Q9=""),"",$P9-$Q9) -> -1 | S9: =IF(OR($R9="",$Q9="",$Q9=0),"",$R9/$Q9) -> -0.028571429 | T9: =IFERROR(INDEX('Asset Register'!$H:$H,MATCH($C9,'Asset Register'!$A:$A,0)),"") -> 350 | U9: =IF($T9="","",$G9*$T9) -> 1750 | V9: =IFERROR($H9/$G9,"") -> 0.2
A10: =IF(B10="","",ROW()-1) -> 9 | B10: 2026-07-09 | C10: EX-2001 | D10: =IFERROR(INDEX('Asset Register'!$B:$B,MATCH($C10,'Asset Register'!$A:$A,0)),"") -> Excavator (Komatsu PC200) | E10: =IFERROR(INDEX('Asset Register'!$C:$C,MATCH($C10,'Asset Register'!$A:$A,0)),"") -> Machinery | F10: =IFERROR(INDEX('Asset Register'!$D:$D,MATCH($C10,'Asset Register'!$A:$A,0)),"") -> Excavator | G10: 7 | H10: 1 | I10: 0 | J10: =IFERROR($G10/($G10+$I10),"") -> 1 | K10: =IFERROR($G10/($G10+$H10+$I10),"") -> 0.875 | L10: =IF($J10="","",1-$J10) -> 0 | O10: =IFERROR(INDEX('Asset Register'!$G:$G,MATCH($C10,'Asset Register'!$A:$A,0)),"") -> 22 | P10: 158 | Q10: =IF($O10="","",$O10*$G10) -> 154 | R10: =IF(OR($P10="",$Q10=""),"",$P10-$Q10) -> 4 | S10: =IF(OR($R10="",$Q10="",$Q10=0),"",$R10/$Q10) -> 0.025974026 | T10: =IFERROR(INDEX('Asset Register'!$H:$H,MATCH($C10,'Asset Register'!$A:$A,0)),"") -> 2200 | U10: =IF($T10="","",$G10*$T10) -> 15400 | V10: =IFERROR($H10/$G10,"") -> 0.14285714
A11: =IF(B11="","",ROW()-1) -> 10 | B11: 2026-07-09 | C11: GD-3001 | D11: =IFERROR(INDEX('Asset Register'!$B:$B,MATCH($C11,'Asset Register'!$A:$A,0)),"") -> Grader (CAT 140K) | E11: =IFERROR(INDEX('Asset Register'!$C:$C,MATCH($C11,'Asset Register'!$A:$A,0)),"") -> Machinery | F11: =IFERROR(INDEX('Asset Register'!$D:$D,MATCH($C11,'Asset Register'!$A:$A,0)),"") -> Grader | G11: 6 | H11: 2 | I11: 0 | J11: =IFERROR($G11/($G11+$I11),"") -> 1 | K11: =IFERROR($G11/($G11+$H11+$I11),"") -> 0.75 | L11: =IF($J11="","",1-$J11) -> 0 | O11: =IFERROR(INDEX('Asset Register'!$G:$G,MATCH($C11,'Asset Register'!$A:$A,0)),"") -> 20 | P11: 128 | Q11: =IF($O11="","",$O11*$G11) -> 120 | R11: =IF(OR($P11="",$Q11=""),"",$P11-$Q11) -> 8 | S11: =IF(OR($R11="",$Q11="",$Q11=0),"",$R11/$Q11) -> 0.066666667 | T11: =IFERROR(INDEX('Asset Register'!$H:$H,MATCH($C11,'Asset Register'!$A:$A,0)),"") -> 2000 | U11: =IF($T11="","",$G11*$T11) -> 12000 | V11: =IFERROR($H11/$G11,"") -> 0.33333333
A12: =IF(B12="","",ROW()-1) -> 11 | B12: 2026-07-09 | C12: LD-4001 | D12: =IFERROR(INDEX('Asset Register'!$B:$B,MATCH($C12,'Asset Register'!$A:$A,0)),"") -> Wheel Loader (CAT 950) | E12: =IFERROR(INDEX('Asset Register'!$C:$C,MATCH($C12,'Asset Register'!$A:$A,0)),"") -> Machinery | F12: =IFERROR(INDEX('Asset Register'!$D:$D,MATCH($C12,'Asset Register'!$A:$A,0)),"") -> Loader | G12: 6.5 | H12: 1.5 | I12: 0 | J12: =IFERROR($G12/($G12+$I12),"") -> 1 | K12: =IFERROR($G12/($G12+$H12+$I12),"") -> 0.8125 | L12: =IF($J12="","",1-$J12) -> 0 | O12: =IFERROR(INDEX('Asset Register'!$G:$G,MATCH($C12,'Asset Register'!$A:$A,0)),"") -> 18 | P12: 122 | Q12: =IF($O12="","",$O12*$G12) -> 117 | R12: =IF(OR($P12="",$Q12=""),"",$P12-$Q12) -> 5 | S12: =IF(OR($R12="",$Q12="",$Q12=0),"",$R12/$Q12) -> 0.042735043 | T12: =IFERROR(INDEX('Asset Register'!$H:$H,MATCH($C12,'Asset Register'!$A:$A,0)),"") -> 1900 | U12: =IF($T12="","",$G12*$T12) -> 12350 | V12: =IFERROR($H12/$G12,"") -> 0.23076923
A13: =IF(B13="","",ROW()-1) -> 12 | B13: 2026-07-09 | C13: GN-5001 | D13: =IFERROR(INDEX('Asset Register'!$B:$B,MATCH($C13,'Asset Register'!$A:$A,0)),"") -> Standby Generator 150KVA | E13: =IFERROR(INDEX('Asset Register'!$C:$C,MATCH($C13,'Asset Register'!$A:$A,0)),"") -> Others | F13: =IFERROR(INDEX('Asset Register'!$D:$D,MATCH($C13,'Asset Register'!$A:$A,0)),"") -> Generator | G13: 8 | H13: 0 | I13: 0 | J13: =IFERROR($G13/($G13+$I13),"") -> 1 | K13: =IFERROR($G13/($G13+$H13+$I13),"") -> 1 | L13: =IF($J13="","",1-$J13) -> 0 | O13: =IFERROR(INDEX('Asset Register'!$G:$G,MATCH($C13,'Asset Register'!$A:$A,0)),"") -> 12 | P13: 100 | Q13: =IF($O13="","",$O13*$G13) -> 96 | R13: =IF(OR($P13="",$Q13=""),"",$P13-$Q13) -> 4 | S13: =IF(OR($R13="",$Q13="",$Q13=0),"",$R13/$Q13) -> 0.041666667 | T13: =IFERROR(INDEX('Asset Register'!$H:$H,MATCH($C13,'Asset Register'!$A:$A,0)),"") -> 300 | U13: =IF($T13="","",$G13*$T13) -> 2400 | V13: =IFERROR($H13/$G13,"") -> 0
A14: =IF(B14="","",ROW()-1) -> 13 | B14: 2026-07-09 | C14: AC-6001 | D14: =IFERROR(INDEX('Asset Register'!$B:$B,MATCH($C14,'Asset Register'!$A:$A,0)),"") -> Air Compressor Unit 1 | E14: =IFERROR(INDEX('Asset Register'!$C:$C,MATCH($C14,'Asset Register'!$A:$A,0)),"") -> Others | F14: =IFERROR(INDEX('Asset Register'!$D:$D,MATCH($C14,'Asset Register'!$A:$A,0)),"") -> Air Compressor | G14: 8 | H14: 0 | I14: 0 | J14: =IFERROR($G14/($G14+$I14),"") -> 1 | K14: =IFERROR($G14/($G14+$H14+$I14),"") -> 1 | L14: =IF($J14="","",1-$J14) -> 0 | O14: =IFERROR(INDEX('Asset Register'!$G:$G,MATCH($C14,'Asset Register'!$A:$A,0)),"") -> 8 | P14: 66 | Q14: =IF($O14="","",$O14*$G14) -> 64 | R14: =IF(OR($P14="",$Q14=""),"",$P14-$Q14) -> 2 | S14: =IF(OR($R14="",$Q14="",$Q14=0),"",$R14/$Q14) -> 0.03125 | T14: =IFERROR(INDEX('Asset Register'!$H:$H,MATCH($C14,'Asset Register'!$A:$A,0)),"") -> 250 | U14: =IF($T14="","",$G14*$T14) -> 2000 | V14: =IFERROR($H14/$G14,"") -> 0
A15: =IF(B15="","",ROW()-1) -> 14 | B15: 2026-07-09 | C15: HT-7001 | D15: =IFERROR(INDEX('Asset Register'!$B:$B,MATCH($C15,'Asset Register'!$A:$A,0)),"") -> Heavy Fuel Tanker | E15: =IFERROR(INDEX('Asset Register'!$C:$C,MATCH($C15,'Asset Register'!$A:$A,0)),"") -> Heavy | F15: =IFERROR(INDEX('Asset Register'!$D:$D,MATCH($C15,'Asset Register'!$A:$A,0)),"") -> Heavy Truck | G15: 7 | H15: 1 | I15: 0 | J15: =IFERROR($G15/($G15+$I15),"") -> 1 | K15: =IFERROR($G15/($G15+$H15+$I15),"") -> 0.875 | L15: =IF($J15="","",1-$J15) -> 0 | O15: =IFERROR(INDEX('Asset Register'!$G:$G,MATCH($C15,'Asset Register'!$A:$A,0)),"") -> 30 | P15: 205 | Q15: =IF($O15="","",$O15*$G15) -> 210 | R15: =IF(OR($P15="",$Q15=""),"",$P15-$Q15) -> -5 | S15: =IF(OR($R15="",$Q15="",$Q15=0),"",$R15/$Q15) -> -0.023809524 | T15: =IFERROR(INDEX('Asset Register'!$H:$H,MATCH($C15,'Asset Register'!$A:$A,0)),"") -> 1600 | U15: =IF($T15="","",$G15*$T15) -> 11200 | V15: =IFERROR($H15/$G15,"") -> 0.14285714
A16: =IF(B16="","",ROW()-1) -> 15 | B16: 2026-07-09 | C16: EL-8001 | D16: =IFERROR(INDEX('Asset Register'!$B:$B,MATCH($C16,'Asset Register'!$A:$A,0)),"") -> Site Electrical Panel | E16: =IFERROR(INDEX('Asset Register'!$C:$C,MATCH($C16,'Asset Register'!$A:$A,0)),"") -> Others | F16: =IFERROR(INDEX('Asset Register'!$D:$D,MATCH($C16,'Asset Register'!$A:$A,0)),"") -> Electrical & Electronics | G16: 8 | H16: 0 | I16: 0 | J16: =IFERROR($G16/($G16+$I16),"") -> 1 | K16: =IFERROR($G16/($G16+$H16+$I16),"") -> 1 | L16: =IF($J16="","",1-$J16) -> 0 | O16: =IFERROR(INDEX('Asset Register'!$G:$G,MATCH($C16,'Asset Register'!$A:$A,0)),"") -> 0 | Q16: =IF($O16="","",$O16*$G16) -> 0 | R16: =IF(OR($P16="",$Q16=""),"",$P16-$Q16) | S16: =IF(OR($R16="",$Q16="",$Q16=0),"",$R16/$Q16) | T16: =IFERROR(INDEX('Asset Register'!$H:$H,MATCH($C16,'Asset Register'!$A:$A,0)),"") -> 200 | U16: =IF($T16="","",$G16*$T16) -> 1600 | V16: =IFERROR($H16/$G16,"") -> 0
A17: =IF(B17="","",ROW()-1) | D17: =IF($C17="","",IFERROR(INDEX('Asset Register'!$B:$B,MATCH($C17,'Asset Register'!$A:$A,0)),"")) | E17: =IF($C17="","",IFERROR(INDEX('Asset Register'!$C:$C,MATCH($C17,'Asset Register'!$A:$A,0)),"")) | F17: =IF($C17="","",IFERROR(INDEX('Asset Register'!$D:$D,MATCH($C17,'Asset Register'!$A:$A,0)),"")) | J17: =IF(OR($G17="",$G17+$I17=0),"",$G17/($G17+$I17)) | K17: =IF(OR($G17="",$G17+$H17+$I17=0),"",$G17/($G17+$H17+$I17)) | L17: =IF($J17="","",1-$J17) | O17: =IF($C17="","",IFERROR(INDEX('Asset Register'!$G:$G,MATCH($C17,'Asset Register'!$A:$A,0)),"")) | Q17: =IF($O17="","",$O17*$G17) | R17: =IF(OR($P17="",$Q17=""),"",$P17-$Q17) | S17: =IF(OR($R17="",$Q17="",$Q17=0),"",$R17/$Q17) | T17: =IF($C17="","",IFERROR(INDEX('Asset Register'!$H:$H,MATCH($C17,'Asset Register'!$A:$A,0)),"")) | U17: =IF($T17="","",$G17*$T17) | V17: =IFERROR($H17/$G17,"")
A18: =IF(B18="","",ROW()-1) | D18: =IF($C18="","",IFERROR(INDEX('Asset Register'!$B:$B,MATCH($C18,'Asset Register'!$A:$A,0)),"")) | E18: =IF($C18="","",IFERROR(INDEX('Asset Register'!$C:$C,MATCH($C18,'Asset Register'!$A:$A,0)),"")) | F18: =IF($C18="","",IFERROR(INDEX('Asset Register'!$D:$D,MATCH($C18,'Asset Register'!$A:$A,0)),"")) | J18: =IF(OR($G18="",$G18+$I18=0),"",$G18/($G18+$I18)) | K18: =IF(OR($G18="",$G18+$H18+$I18=0),"",$G18/($G18+$H18+$I18)) | L18: =IF($J18="","",1-$J18) | O18: =IF($C18="","",IFERROR(INDEX('Asset Register'!$G:$G,MATCH($C18,'Asset Register'!$A:$A,0)),"")) | Q18: =IF($O18="","",$O18*$G18) | R18: =IF(OR($P18="",$Q18=""),"",$P18-$Q18) | S18: =IF(OR($R18="",$Q18="",$Q18=0),"",$R18/$Q18) | T18: =IF($C18="","",IFERROR(INDEX('Asset Register'!$H:$H,MATCH($C18,'Asset Register'!$A:$A,0)),"")) | U18: =IF($T18="","",$G18*$T18) | V18: =IFERROR($H18/$G18,"")
A19: =IF(B19="","",ROW()-1) | D19: =IF($C19="","",IFERROR(INDEX('Asset Register'!$B:$B,MATCH($C19,'Asset Register'!$A:$A,0)),"")) | E19: =IF($C19="","",IFERROR(INDEX('Asset Register'!$C:$C,MATCH($C19,'Asset Register'!$A:$A,0)),"")) | F19: =IF($C19="","",IFERROR(INDEX('Asset Register'!$D:$D,MATCH($C19,'Asset Register'!$A:$A,0)),"")) | J19: =IF(OR($G19="",$G19+$I19=0),"",$G19/($G19+$I19)) | K19: =IF(OR($G19="",$G19+$H19+$I19=0),"",$G19/($G19+$H19+$I19)) | L19: =IF($J19="","",1-$J19) | O19: =IF($C19="","",IFERROR(INDEX('Asset Register'!$G:$G,MATCH($C19,'Asset Register'!$A:$A,0)),"")) | Q19: =IF($O19="","",$O19*$G19) | R19: =IF(OR($P19="",$Q19=""),"",$P19-$Q19) | S19: =IF(OR($R19="",$Q19="",$Q19=0),"",$R19/$Q19) | T19: =IF($C19="","",IFERROR(INDEX('Asset Register'!$H:$H,MATCH($C19,'Asset Register'!$A:$A,0)),"")) | U19: =IF($T19="","",$G19*$T19) | V19: =IFERROR($H19/$G19,"")
A20: =IF(B20="","",ROW()-1) | D20: =IF($C20="","",IFERROR(INDEX('Asset Register'!$B:$B,MATCH($C20,'Asset Register'!$A:$A,0)),"")) | E20: =IF($C20="","",IFERROR(INDEX('Asset Register'!$C:$C,MATCH($C20,'Asset Register'!$A:$A,0)),"")) | F20: =IF($C20="","",IFERROR(INDEX('Asset Register'!$D:$D,MATCH($C20,'Asset Register'!$A:$A,0)),"")) | J20: =IF(OR($G20="",$G20+$I20=0),"",$G20/($G20+$I20)) | K20: =IF(OR($G20="",$G20+$H20+$I20=0),"",$G20/($G20+$H20+$I20)) | L20: =IF($J20="","",1-$J20) | O20: =IF($C20="","",IFERROR(INDEX('Asset Register'!$G:$G,MATCH($C20,'Asset Register'!$A:$A,0)),"")) | Q20: =IF($O20="","",$O20*$G20) | R20: =IF(OR($P20="",$Q20=""),"",$P20-$Q20) | S20: =IF(OR($R20="",$Q20="",$Q20=0),"",$R20/$Q20) | T20: =IF($C20="","",IFERROR(INDEX('Asset Register'!$H:$H,MATCH($C20,'Asset Register'!$A:$A,0)),"")) | U20: =IF($T20="","",$G20*$T20) | V20: =IFERROR($H20/$G20,"")
A21: =IF(B21="","",ROW()-1) | D21: =IF($C21="","",IFERROR(INDEX('Asset Register'!$B:$B,MATCH($C21,'Asset Register'!$A:$A,0)),"")) | E21: =IF($C21="","",IFERROR(INDEX('Asset Register'!$C:$C,MATCH($C21,'Asset Register'!$A:$A,0)),"")) | F21: =IF($C21="","",IFERROR(INDEX('Asset Register'!$D:$D,MATCH($C21,'Asset Register'!$A:$A,0)),"")) | J21: =IF(OR($G21="",$G21+$I21=0),"",$G21/($G21+$I21)) | K21: =IF(OR($G21="",$G21+$H21+$I21=0),"",$G21/($G21+$H21+$I21)) | L21: =IF($J21="","",1-$J21) | O21: =IF($C21="","",IFERROR(INDEX('Asset Register'!$G:$G,MATCH($C21,'Asset Register'!$A:$A,0)),"")) | Q21: =IF($O21="","",$O21*$G21) | R21: =IF(OR($P21="",$Q21=""),"",$P21-$Q21) | S21: =IF(OR($R21="",$Q21="",$Q21=0),"",$R21/$Q21) | T21: =IF($C21="","",IFERROR(INDEX('Asset Register'!$H:$H,MATCH($C21,'Asset Register'!$A:$A,0)),"")) | U21: =IF($T21="","",$G21*$T21) | V21: =IFERROR($H21/$G21,"")
A22: =IF(B22="","",ROW()-1) | D22: =IF($C22="","",IFERROR(INDEX('Asset Register'!$B:$B,MATCH($C22,'Asset Register'!$A:$A,0)),"")) | E22: =IF($C22="","",IFERROR(INDEX('Asset Register'!$C:$C,MATCH($C22,'Asset Register'!$A:$A,0)),"")) | F22: =IF($C22="","",IFERROR(INDEX('Asset Register'!$D:$D,MATCH($C22,'Asset Register'!$A:$A,0)),"")) | J22: =IF(OR($G22="",$G22+$I22=0),"",$G22/($G22+$I22)) | K22: =IF(OR($G22="",$G22+$H22+$I22=0),"",$G22/($G22+$H22+$I22)) | L22: =IF($J22="","",1-$J22) | O22: =IF($C22="","",IFERROR(INDEX('Asset Register'!$G:$G,MATCH($C22,'Asset Register'!$A:$A,0)),"")) | Q22: =IF($O22="","",$O22*$G22) | R22: =IF(OR($P22="",$Q22=""),"",$P22-$Q22) | S22: =IF(OR($R22="",$Q22="",$Q22=0),"",$R22/$Q22) | T22: =IF($C22="","",IFERROR(INDEX('Asset Register'!$H:$H,MATCH($C22,'Asset Register'!$A:$A,0)),"")) | U22: =IF($T22="","",$G22*$T22) | V22: =IFERROR($H22/$G22,"")
A23: =IF(B23="","",ROW()-1) | D23: =IF($C23="","",IFERROR(INDEX('Asset Register'!$B:$B,MATCH($C23,'Asset Register'!$A:$A,0)),"")) | E23: =IF($C23="","",IFERROR(INDEX('Asset Register'!$C:$C,MATCH($C23,'Asset Register'!$A:$A,0)),"")) | F23: =IF($C23="","",IFERROR(INDEX('Asset Register'!$D:$D,MATCH($C23,'Asset Register'!$A:$A,0)),"")) | J23: =IF(OR($G23="",$G23+$I23=0),"",$G23/($G23+$I23)) | K23: =IF(OR($G23="",$G23+$H23+$I23=0),"",$G23/($G23+$H23+$I23)) | L23: =IF($J23="","",1-$J23) | O23: =IF($C23="","",IFERROR(INDEX('Asset Register'!$G:$G,MATCH($C23,'Asset Register'!$A:$A,0)),"")) | Q23: =IF($O23="","",$O23*$G23) | R23: =IF(OR($P23="",$Q23=""),"",$P23-$Q23) | S23: =IF(OR($R23="",$Q23="",$Q23=0),"",$R23/$Q23) | T23: =IF($C23="","",IFERROR(INDEX('Asset Register'!$H:$H,MATCH($C23,'Asset Register'!$A:$A,0)),"")) | U23: =IF($T23="","",$G23*$T23) | V23: =IFERROR($H23/$G23,"")
A24: =IF(B24="","",ROW()-1) | D24: =IF($C24="","",IFERROR(INDEX('Asset Register'!$B:$B,MATCH($C24,'Asset Register'!$A:$A,0)),"")) | E24: =IF($C24="","",IFERROR(INDEX('Asset Register'!$C:$C,MATCH($C24,'Asset Register'!$A:$A,0)),"")) | F24: =IF($C24="","",IFERROR(INDEX('Asset Register'!$D:$D,MATCH($C24,'Asset Register'!$A:$A,0)),"")) | J24: =IF(OR($G24="",$G24+$I24=0),"",$G24/($G24+$I24)) | K24: =IF(OR($G24="",$G24+$H24+$I24=0),"",$G24/($G24+$H24+$I24)) | L24: =IF($J24="","",1-$J24) | O24: =IF($C24="","",IFERROR(INDEX('Asset Register'!$G:$G,MATCH($C24,'Asset Register'!$A:$A,0)),"")) | Q24: =IF($O24="","",$O24*$G24) | R24: =IF(OR($P24="",$Q24=""),"",$P24-$Q24) | S24: =IF(OR($R24="",$Q24="",$Q24=0),"",$R24/$Q24) | T24: =IF($C24="","",IFERROR(INDEX('Asset Register'!$H:$H,MATCH($C24,'Asset Register'!$A:$A,0)),"")) | U24: =IF($T24="","",$G24*$T24) | V24: =IFERROR($H24/$G24,"")
A25: =IF(B25="","",ROW()-1) | D25: =IF($C25="","",IFERROR(INDEX('Asset Register'!$B:$B,MATCH($C25,'Asset Register'!$A:$A,0)),"")) | E25: =IF($C25="","",IFERROR(INDEX('Asset Register'!$C:$C,MATCH($C25,'Asset Register'!$A:$A,0)),"")) | F25: =IF($C25="","",IFERROR(INDEX('Asset Register'!$D:$D,MATCH($C25,'Asset Register'!$A:$A,0)),"")) | J25: =IF(OR($G25="",$G25+$I25=0),"",$G25/($G25+$I25)) | K25: =IF(OR($G25="",$G25+$H25+$I25=0),"",$G25/($G25+$H25+$I25)) | L25: =IF($J25="","",1-$J25) | O25: =IF($C25="","",IFERROR(INDEX('Asset Register'!$G:$G,MATCH($C25,'Asset Register'!$A:$A,0)),"")) | Q25: =IF($O25="","",$O25*$G25) | R25: =IF(OR($P25="",$Q25=""),"",$P25-$Q25) | S25: =IF(OR($R25="",$Q25="",$Q25=0),"",$R25/$Q25) | T25: =IF($C25="","",IFERROR(INDEX('Asset Register'!$H:$H,MATCH($C25,'Asset Register'!$A:$A,0)),"")) | U25: =IF($T25="","",$G25*$T25) | V25: =IFERROR($H25/$G25,"")
A26: =IF(B26="","",ROW()-1) | D26: =IF($C26="","",IFERROR(INDEX('Asset Register'!$B:$B,MATCH($C26,'Asset Register'!$A:$A,0)),"")) | E26: =IF($C26="","",IFERROR(INDEX('Asset Register'!$C:$C,MATCH($C26,'Asset Register'!$A:$A,0)),"")) | F26: =IF($C26="","",IFERROR(INDEX('Asset Register'!$D:$D,MATCH($C26,'Asset Register'!$A:$A,0)),"")) | J26: =IF(OR($G26="",$G26+$I26=0),"",$G26/($G26+$I26)) | K26: =IF(OR($G26="",$G26+$H26+$I26=0),"",$G26/($G26+$H26+$I26)) | L26: =IF($J26="","",1-$J26) | O26: =IF($C26="","",IFERROR(INDEX('Asset Register'!$G:$G,MATCH($C26,'Asset Register'!$A:$A,0)),"")) | Q26: =IF($O26="","",$O26*$G26) | R26: =IF(OR($P26="",$Q26=""),"",$P26-$Q26) | S26: =IF(OR($R26="",$Q26="",$Q26=0),"",$R26/$Q26) | T26: =IF($C26="","",IFERROR(INDEX('Asset Register'!$H:$H,MATCH($C26,'Asset Register'!$A:$A,0)),"")) | U26: =IF($T26="","",$G26*$T26) | V26: =IFERROR($H26/$G26,"")
A27: =IF(B27="","",ROW()-1) | D27: =IF($C27="","",IFERROR(INDEX('Asset Register'!$B:$B,MATCH($C27,'Asset Register'!$A:$A,0)),"")) | E27: =IF($C27="","",IFERROR(INDEX('Asset Register'!$C:$C,MATCH($C27,'Asset Register'!$A:$A,0)),"")) | F27: =IF($C27="","",IFERROR(INDEX('Asset Register'!$D:$D,MATCH($C27,'Asset Register'!$A:$A,0)),"")) | J27: =IF(OR($G27="",$G27+$I27=0),"",$G27/($G27+$I27)) | K27: =IF(OR($G27="",$G27+$H27+$I27=0),"",$G27/($G27+$H27+$I27)) | L27: =IF($J27="","",1-$J27) | O27: =IF($C27="","",IFERROR(INDEX('Asset Register'!$G:$G,MATCH($C27,'Asset Register'!$A:$A,0)),"")) | Q27: =IF($O27="","",$O27*$G27) | R27: =IF(OR($P27="",$Q27=""),"",$P27-$Q27) | S27: =IF(OR($R27="",$Q27="",$Q27=0),"",$R27/$Q27) | T27: =IF($C27="","",IFERROR(INDEX('Asset Register'!$H:$H,MATCH($C27,'Asset Register'!$A:$A,0)),"")) | U27: =IF($T27="","",$G27*$T27) | V27: =IFERROR($H27/$G27,"")
A28: =IF(B28="","",ROW()-1) | D28: =IF($C28="","",IFERROR(INDEX('Asset Register'!$B:$B,MATCH($C28,'Asset Register'!$A:$A,0)),"")) | E28: =IF($C28="","",IFERROR(INDEX('Asset Register'!$C:$C,MATCH($C28,'Asset Register'!$A:$A,0)),"")) | F28: =IF($C28="","",IFERROR(INDEX('Asset Register'!$D:$D,MATCH($C28,'Asset Register'!$A:$A,0)),"")) | J28: =IF(OR($G28="",$G28+$I28=0),"",$G28/($G28+$I28)) | K28: =IF(OR($G28="",$G28+$H28+$I28=0),"",$G28/($G28+$H28+$I28)) | L28: =IF($J28="","",1-$J28) | O28: =IF($C28="","",IFERROR(INDEX('Asset Register'!$G:$G,MATCH($C28,'Asset Register'!$A:$A,0)),"")) | Q28: =IF($O28="","",$O28*$G28) | R28: =IF(OR($P28="",$Q28=""),"",$P28-$Q28) | S28: =IF(OR($R28="",$Q28="",$Q28=0),"",$R28/$Q28) | T28: =IF($C28="","",IFERROR(INDEX('Asset Register'!$H:$H,MATCH($C28,'Asset Register'!$A:$A,0)),"")) | U28: =IF($T28="","",$G28*$T28) | V28: =IFERROR($H28/$G28,"")
... A500: =IF(B500="","",ROW()-1) | D500: =IF($C500="","",IFERROR(INDEX('Asset Register'!$B:$B,MATCH($C500,'Asset Register'!$A:$A,0)),"")) | E500: =IF($C500="","",IFERROR(INDEX('Asset Register'!$C:$C,MATCH($C500,'Asset Register'!$A:$A,0)),"")) | F500: =IF($C500="","",IFERROR(INDEX('Asset Register'!$D:$D,MATCH($C500,'Asset Register'!$A:$A,0)),"")) | J500: =IF(OR($G500="",$G500+$I500=0),"",$G500/($G500+$I500)) | K500: =IF(OR($G500="",$G500+$H500+$I500=0),"",$G500/($G500+$H500+$I500)) | L500: =IF($J500="","",1-$J500) | O500: =IF($C500="","",IFERROR(INDEX('Asset Register'!$G:$G,MATCH($C500,'Asset Register'!$A:$A,0)),"")) | Q500: =IF($O500="","",$O500*$G500) | R500: =IF(OR($P500="",$Q500=""),"",$P500-$Q500) | S500: =IF(OR($R500="",$Q500="",$Q500=0),"",$R500/$Q500) | T500: =IF($C500="","",IFERROR(INDEX('Asset Register'!$H:$H,MATCH($C500,'Asset Register'!$A:$A,0)),"")) | U500: =IF($T500="","",$G500*$T500) | V500: =IFERROR($H500/$G500,"")

Sheet Maintenance Log
A1: Log ID | B1: Date | C1: Asset ID | D1: Asset Name | E1: Category | F1: Equipment Type | G1: Maintenance Task | H1: Maintenance Group | I1: Maintenance Type | J1: Standard Time Ref (Hrs) | K1: Time Used (Hrs) | L1: Technicians Assigned | M1: Technician Rate/Hr (ETB) | N1: Labor Cost (ETB) | O1: Part 1 Name | P1: Part 1 Qty | Q1: Part 1 Unit Cost (ETB) | R1: Part 1 Line Cost (ETB) | S1: Part 2 Name | T1: Part 2 Qty | U1: Part 2 Unit Cost (ETB) | V1: Part 2 Line Cost (ETB) | W1: Part 3 Name | X1: Part 3 Qty | Y1: Part 3 Unit Cost (ETB) | Z1: Part 3 Line Cost (ETB) | AA1: Other Cost (ETB) | AB1: Total Parts Cost (ETB) | AC1: Total Cost (ETB) | AD1: Cost per Hour (ETB) | AE1: Remarks | AF1: TypeKey (helper)
A2: =IF(B2="","",ROW()-1) -> 1 | B2: 2026-07-02 | C2: AA-65266 | D2: =IFERROR(INDEX('Asset Register'!$B:$B,MATCH($C2,'Asset Register'!$A:$A,0)),"") -> Bull Dozer (CAT) | E2: Machinery | F2: Dozer | G2: Repair Track Link(single) | H2: =IFERROR(INDEX('Task Master'!$E:$E,MATCH($F2&"||"&$G2,'Task Master'!$K:$K,0)),"") -> I. Hydraulic and Power Train System | I2: =IFERROR(INDEX('Task Master'!$F:$F,MATCH($F2&"||"&$G2,'Task Master'!$K:$K,0)),"") -> Corrective | J2: =IFERROR(INDEX('Task Master'!$H:$H,MATCH($F2&"||"&$G2,'Task Master'!$K:$K,0)),"") -> 9 | K2: 6 | L2: 2 | M2: 250 | N2: =IF(OR($K2="",$L2="",$M2=""),"",$K2*$L2*$M2) -> 3000 | O2: Track link assembly | P2: 2 | Q2: 7400 | R2: =IF(OR($P2="",$Q2=""),0,$P2*$Q2) -> 14800 | V2: =IF(OR($T2="",$U2=""),0,$T2*$U2) -> 0 | Z2: =IF(OR($X2="",$Y2=""),0,$X2*$Y2) -> 0 | AA2: 500 | AB2: =$R2+$V2+$Z2 -> 14800 | AC2: =IF($B2="","",$AB2+$AA2+$N2) -> 18300 | AD2: =IF(OR($K2="",$K2=0,$AC2=""),"",$AC2/$K2) -> 3050 | AE2: Awaiting parts allocation | AF2: =IFERROR(INDEX('Task Master'!$D:$D,MATCH($F2,'Task Master'!$C:$C,0)),"") -> Dozer
A3: =IF(B3="","",ROW()-1) -> 2 | B3: 2026-07-05 | C3: AA-9018 | D3: =IFERROR(INDEX('Asset Register'!$B:$B,MATCH($C3,'Asset Register'!$A:$A,0)),"") -> Bull Dozer (CAT) | E3: Machinery | F3: Earth Moving Machinery (General PM & Engine) | G3: Engine Tune-Up | H3: =IFERROR(INDEX('Task Master'!$E:$E,MATCH($F3&"||"&$G3,'Task Master'!$K:$K,0)),"") -> VI. Engine Repair | I3: =IFERROR(INDEX('Task Master'!$F:$F,MATCH($F3&"||"&$G3,'Task Master'!$K:$K,0)),"") -> Corrective | J3: =IFERROR(INDEX('Task Master'!$H:$H,MATCH($F3&"||"&$G3,'Task Master'!$K:$K,0)),"") -> 8 | K3: 5 | L3: 2 | M3: 250 | N3: =IF(OR($K3="",$L3="",$M3=""),"",$K3*$L3*$M3) -> 2500 | O3: Injector set | P3: 1 | Q3: 3500 | R3: =IF(OR($P3="",$Q3=""),0,$P3*$Q3) -> 3500 | S3: Spark/glow plugs (set of 4) | T3: 4 | U3: 50 | V3: =IF(OR($T3="",$U3=""),0,$T3*$U3) -> 200 | Z3: =IF(OR($X3="",$Y3=""),0,$X3*$Y3) -> 0 | AA3: 0 | AB3: =$R3+$V3+$Z3 -> 3700 | AC3: =IF($B3="","",$AB3+$AA3+$N3) -> 6200 | AD3: =IF(OR($K3="",$K3=0,$AC3=""),"",$AC3/$K3) -> 1240 | AE3: Calibrated by engineer | AF3: =IFERROR(INDEX('Task Master'!$D:$D,MATCH($F3,'Task Master'!$C:$C,0)),"") -> Earth_Moving_Machinery_General_PM_Engine
A4: =IF(B4="","",ROW()-1) -> 3 | B4: 2026-07-06 | C4: AA-65585 | D4: =IFERROR(INDEX('Asset Register'!$B:$B,MATCH($C4,'Asset Register'!$A:$A,0)),"") -> Dump Truck (Volvo) | E4: Heavy | F4: Heavy Truck | G4: Servicing Front & rear Brakes, Hoses, Lines and Hand Brakes | H4: =IFERROR(INDEX('Task Master'!$E:$E,MATCH($F4&"||"&$G4,'Task Master'!$K:$K,0)),"") -> II. General Service B = 10,000 KM | I4: =IFERROR(INDEX('Task Master'!$F:$F,MATCH($F4&"||"&$G4,'Task Master'!$K:$K,0)),"") -> Preventive | J4: =IFERROR(INDEX('Task Master'!$H:$H,MATCH($F4&"||"&$G4,'Task Master'!$K:$K,0)),"") -> 18 | K4: 4 | L4: 2 | M4: 200 | N4: =IF(OR($K4="",$L4="",$M4=""),"",$K4*$L4*$M4) -> 1600 | R4: =IF(OR($P4="",$Q4=""),0,$P4*$Q4) -> 0 | V4: =IF(OR($T4="",$U4=""),0,$T4*$U4) -> 0 | Z4: =IF(OR($X4="",$Y4=""),0,$X4*$Y4) -> 0 | AA4: 0 | AB4: =$R4+$V4+$Z4 -> 0 | AC4: =IF($B4="","",$AB4+$AA4+$N4) -> 1600 | AD4: =IF(OR($K4="",$K4=0,$AC4=""),"",$AC4/$K4) -> 400 | AE4: Routine check, no issues | AF4: =IFERROR(INDEX('Task Master'!$D:$D,MATCH($F4,'Task Master'!$C:$C,0)),"") -> Heavy_Truck
A5: =IF(B5="","",ROW()-1) -> 4 | B5: 2026-07-06 | C5: AA-60042 | D5: =IFERROR(INDEX('Asset Register'!$B:$B,MATCH($C5,'Asset Register'!$A:$A,0)),"") -> Bull Dozer (Komatsu) | E5: Machinery | F5: Earth Moving Machinery (General PM & Engine) | G5: Grease Service | H5: =IFERROR(INDEX('Task Master'!$E:$E,MATCH($F5&"||"&$G5,'Task Master'!$K:$K,0)),"") -> II. Every 250 Service Hours or Monthly | I5: =IFERROR(INDEX('Task Master'!$F:$F,MATCH($F5&"||"&$G5,'Task Master'!$K:$K,0)),"") -> Preventive | J5: =IFERROR(INDEX('Task Master'!$H:$H,MATCH($F5&"||"&$G5,'Task Master'!$K:$K,0)),"") -> 2 | K5: 2 | L5: 1 | M5: 250 | N5: =IF(OR($K5="",$L5="",$M5=""),"",$K5*$L5*$M5) -> 500 | O5: Grease cartridge | P5: 2 | Q5: 150 | R5: =IF(OR($P5="",$Q5=""),0,$P5*$Q5) -> 300 | V5: =IF(OR($T5="",$U5=""),0,$T5*$U5) -> 0 | Z5: =IF(OR($X5="",$Y5=""),0,$X5*$Y5) -> 0 | AA5: 0 | AB5: =$R5+$V5+$Z5 -> 300 | AC5: =IF($B5="","",$AB5+$AA5+$N5) -> 800 | AD5: =IF(OR($K5="",$K5=0,$AC5=""),"",$AC5/$K5) -> 400 | AE5: Operable status | AF5: =IFERROR(INDEX('Task Master'!$D:$D,MATCH($F5,'Task Master'!$C:$C,0)),"") -> Earth_Moving_Machinery_General_PM_Engine
A6: =IF(B6="","",ROW()-1) -> 5 | B6: 2026-07-07 | C6: LV-1001 | D6: =IFERROR(INDEX('Asset Register'!$B:$B,MATCH($C6,'Asset Register'!$A:$A,0)),"") -> Toyota Land Cruiser | E6: Light | F6: Automobile | G6: Changing the Engine Oil & Oil filter | H6: =IFERROR(INDEX('Task Master'!$E:$E,MATCH($F6&"||"&$G6,'Task Master'!$K:$K,0)),"") -> I. General Service A = 5,000 KM | I6: =IFERROR(INDEX('Task Master'!$F:$F,MATCH($F6&"||"&$G6,'Task Master'!$K:$K,0)),"") -> Preventive | J6: =IFERROR(INDEX('Task Master'!$H:$H,MATCH($F6&"||"&$G6,'Task Master'!$K:$K,0)),"") -> 1.5 | K6: 1.5 | L6: 1 | M6: 150 | N6: =IF(OR($K6="",$L6="",$M6=""),"",$K6*$L6*$M6) -> 225 | O6: Engine oil 5L | P6: 5 | Q6: 150 | R6: =IF(OR($P6="",$Q6=""),0,$P6*$Q6) -> 750 | S6: Oil filter | T6: 1 | U6: 500 | V6: =IF(OR($T6="",$U6=""),0,$T6*$U6) -> 500 | Z6: =IF(OR($X6="",$Y6=""),0,$X6*$Y6) -> 0 | AA6: 0 | AB6: =$R6+$V6+$Z6 -> 1250 | AC6: =IF($B6="","",$AB6+$AA6+$N6) -> 1475 | AD6: =IF(OR($K6="",$K6=0,$AC6=""),"",$AC6/$K6) -> 983.33333 | AE6: Standard 5,000 km service | AF6: =IFERROR(INDEX('Task Master'!$D:$D,MATCH($F6,'Task Master'!$C:$C,0)),"") -> Automobile
A7: =IF(B7="","",ROW()-1) -> 6 | B7: 2026-07-07 | C7: LV-1002 | D7: =IFERROR(INDEX('Asset Register'!$B:$B,MATCH($C7,'Asset Register'!$A:$A,0)),"") -> Toyota Hilux Pickup | E7: Light | F7: Pick Up / Station Wagon / Mini Bus | G7: Checking Front & rear Brakes, Hoses, Lines and Hand Brakes | H7: =IFERROR(INDEX('Task Master'!$E:$E,MATCH($F7&"||"&$G7,'Task Master'!$K:$K,0)),"") -> I. General Service A = 5,000 KM | I7: =IFERROR(INDEX('Task Master'!$F:$F,MATCH($F7&"||"&$G7,'Task Master'!$K:$K,0)),"") -> Preventive | J7: =IFERROR(INDEX('Task Master'!$H:$H,MATCH($F7&"||"&$G7,'Task Master'!$K:$K,0)),"") -> 4 | K7: 4 | L7: 2 | M7: 150 | N7: =IF(OR($K7="",$L7="",$M7=""),"",$K7*$L7*$M7) -> 1200 | O7: Brake pad set (front) | P7: 1 | Q7: 2100 | R7: =IF(OR($P7="",$Q7=""),0,$P7*$Q7) -> 2100 | V7: =IF(OR($T7="",$U7=""),0,$T7*$U7) -> 0 | Z7: =IF(OR($X7="",$Y7=""),0,$X7*$Y7) -> 0 | AA7: 0 | AB7: =$R7+$V7+$Z7 -> 2100 | AC7: =IF($B7="","",$AB7+$AA7+$N7) -> 3300 | AD7: =IF(OR($K7="",$K7=0,$AC7=""),"",$AC7/$K7) -> 825 | AE7: Pads replaced | AF7: =IFERROR(INDEX('Task Master'!$D:$D,MATCH($F7,'Task Master'!$C:$C,0)),"") -> Pick_Up_Station_Wagon_Mini_Bus
A8: =IF(B8="","",ROW()-1) -> 7 | B8: 2026-07-08 | C8: EX-2001 | D8: =IFERROR(INDEX('Asset Register'!$B:$B,MATCH($C8,'Asset Register'!$A:$A,0)),"") -> Excavator (Komatsu PC200) | E8: Machinery | F8: Excavator | G8: Repair Track chain one side (Shoe) | H8: =IFERROR(INDEX('Task Master'!$E:$E,MATCH($F8&"||"&$G8,'Task Master'!$K:$K,0)),"") -> I. Hydraulic and Power Train System | I8: =IFERROR(INDEX('Task Master'!$F:$F,MATCH($F8&"||"&$G8,'Task Master'!$K:$K,0)),"") -> Corrective | J8: =IFERROR(INDEX('Task Master'!$H:$H,MATCH($F8&"||"&$G8,'Task Master'!$K:$K,0)),"") -> 60 | K8: 60 | L8: 2 | M8: 300 | N8: =IF(OR($K8="",$L8="",$M8=""),"",$K8*$L8*$M8) -> 36000 | O8: Track chain + shoe set | P8: 1 | Q8: 44000 | R8: =IF(OR($P8="",$Q8=""),0,$P8*$Q8) -> 44000 | V8: =IF(OR($T8="",$U8=""),0,$T8*$U8) -> 0 | Z8: =IF(OR($X8="",$Y8=""),0,$X8*$Y8) -> 0 | AA8: 4000 | AB8: =$R8+$V8+$Z8 -> 44000 | AC8: =IF($B8="","",$AB8+$AA8+$N8) -> 84000 | AD8: =IF(OR($K8="",$K8=0,$AC8=""),"",$AC8/$K8) -> 1400 | AE8: Major repair, 2-day job | AF8: =IFERROR(INDEX('Task Master'!$D:$D,MATCH($F8,'Task Master'!$C:$C,0)),"") -> Excavator
A9: =IF(B9="","",ROW()-1) -> 8 | B9: 2026-07-08 | C9: GD-3001 | D9: =IFERROR(INDEX('Asset Register'!$B:$B,MATCH($C9,'Asset Register'!$A:$A,0)),"") -> Grader (CAT 140K) | E9: Machinery | F9: Grader | G9: Repair Circle drive motor | H9: =IFERROR(INDEX('Task Master'!$E:$E,MATCH($F9&"||"&$G9,'Task Master'!$K:$K,0)),"") -> I. Hydraulic System and Power Train System | I9: =IFERROR(INDEX('Task Master'!$F:$F,MATCH($F9&"||"&$G9,'Task Master'!$K:$K,0)),"") -> Corrective | J9: =IFERROR(INDEX('Task Master'!$H:$H,MATCH($F9&"||"&$G9,'Task Master'!$K:$K,0)),"") -> 12 | K9: 14 | L9: 2 | M9: 280 | N9: =IF(OR($K9="",$L9="",$M9=""),"",$K9*$L9*$M9) -> 7840 | O9: Circle drive motor | P9: 1 | Q9: 8500 | R9: =IF(OR($P9="",$Q9=""),0,$P9*$Q9) -> 8500 | S9: Seal kit | T9: 1 | U9: 500 | V9: =IF(OR($T9="",$U9=""),0,$T9*$U9) -> 500 | Z9: =IF(OR($X9="",$Y9=""),0,$X9*$Y9) -> 0 | AA9: 0 | AB9: =$R9+$V9+$Z9 -> 9000 | AC9: =IF($B9="","",$AB9+$AA9+$N9) -> 16840 | AD9: =IF(OR($K9="",$K9=0,$AC9=""),"",$AC9/$K9) -> 1202.8571 | AE9: Hydraulic drive motor rebuilt | AF9: =IFERROR(INDEX('Task Master'!$D:$D,MATCH($F9,'Task Master'!$C:$C,0)),"") -> Grader
A10: =IF(B10="","",ROW()-1) -> 9 | B10: 2026-07-09 | C10: LD-4001 | D10: =IFERROR(INDEX('Asset Register'!$B:$B,MATCH($C10,'Asset Register'!$A:$A,0)),"") -> Wheel Loader (CAT 950) | E10: Machinery | F10: Loader | G10: Replace Brake Pad | H10: =IFERROR(INDEX('Task Master'!$E:$E,MATCH($F10&"||"&$G10,'Task Master'!$K:$K,0)),"") -> I. Hydraulic and Power Train System | I10: =IFERROR(INDEX('Task Master'!$F:$F,MATCH($F10&"||"&$G10,'Task Master'!$K:$K,0)),"") -> Corrective | J10: =IFERROR(INDEX('Task Master'!$H:$H,MATCH($F10&"||"&$G10,'Task Master'!$K:$K,0)),"") -> 6 | K10: 6 | L10: 2 | M10: 250 | N10: =IF(OR($K10="",$L10="",$M10=""),"",$K10*$L10*$M10) -> 3000 | O10: Brake pad set | P10: 1 | Q10: 4200 | R10: =IF(OR($P10="",$Q10=""),0,$P10*$Q10) -> 4200 | V10: =IF(OR($T10="",$U10=""),0,$T10*$U10) -> 0 | Z10: =IF(OR($X10="",$Y10=""),0,$X10*$Y10) -> 0 | AA10: 0 | AB10: =$R10+$V10+$Z10 -> 4200 | AC10: =IF($B10="","",$AB10+$AA10+$N10) -> 7200 | AD10: =IF(OR($K10="",$K10=0,$AC10=""),"",$AC10/$K10) -> 1200 | AE10: Scheduled brake service | AF10: =IFERROR(INDEX('Task Master'!$D:$D,MATCH($F10,'Task Master'!$C:$C,0)),"") -> Loader
A11: =IF(B11="","",ROW()-1) -> 10 | B11: 2026-07-09 | C11: GN-5001 | D11: =IFERROR(INDEX('Asset Register'!$B:$B,MATCH($C11,'Asset Register'!$A:$A,0)),"") -> Standby Generator 150KVA | E11: Others | F11: Generator | G11: Change Engine Oil With Filter | H11: =IFERROR(INDEX('Task Master'!$E:$E,MATCH($F11&"||"&$G11,'Task Master'!$K:$K,0)),"") -> II. Every 250 Service Hours or Monthly | I11: =IFERROR(INDEX('Task Master'!$F:$F,MATCH($F11&"||"&$G11,'Task Master'!$K:$K,0)),"") -> Preventive | J11: =IFERROR(INDEX('Task Master'!$H:$H,MATCH($F11&"||"&$G11,'Task Master'!$K:$K,0)),"") -> 2 | K11: 2 | L11: 2 | M11: 180 | N11: =IF(OR($K11="",$L11="",$M11=""),"",$K11*$L11*$M11) -> 720 | O11: Engine oil 4L | P11: 4 | Q11: 150 | R11: =IF(OR($P11="",$Q11=""),0,$P11*$Q11) -> 600 | S11: Oil filter | T11: 1 | U11: 300 | V11: =IF(OR($T11="",$U11=""),0,$T11*$U11) -> 300 | Z11: =IF(OR($X11="",$Y11=""),0,$X11*$Y11) -> 0 | AA11: 0 | AB11: =$R11+$V11+$Z11 -> 900 | AC11: =IF($B11="","",$AB11+$AA11+$N11) -> 1620 | AD11: =IF(OR($K11="",$K11=0,$AC11=""),"",$AC11/$K11) -> 810 | AE11: Monthly PM | AF11: =IFERROR(INDEX('Task Master'!$D:$D,MATCH($F11,'Task Master'!$C:$C,0)),"") -> Generator
A12: =IF(B12="","",ROW()-1) -> 11 | B12: 2026-07-09 | C12: AC-6001 | D12: =IFERROR(INDEX('Asset Register'!$B:$B,MATCH($C12,'Asset Register'!$A:$A,0)),"") -> Air Compressor Unit 1 | E12: Others | F12: Air Compressor | G12: Change compressor oil | H12: =IFERROR(INDEX('Task Master'!$E:$E,MATCH($F12&"||"&$G12,'Task Master'!$K:$K,0)),"") -> III. Every 500 Service Hours or 3 months | I12: =IFERROR(INDEX('Task Master'!$F:$F,MATCH($F12&"||"&$G12,'Task Master'!$K:$K,0)),"") -> Preventive | J12: =IFERROR(INDEX('Task Master'!$H:$H,MATCH($F12&"||"&$G12,'Task Master'!$K:$K,0)),"") -> 1.5 | K12: 1.5 | L12: 2 | M12: 180 | N12: =IF(OR($K12="",$L12="",$M12=""),"",$K12*$L12*$M12) -> 540 | O12: Compressor oil 4L | P12: 4 | Q12: 150 | R12: =IF(OR($P12="",$Q12=""),0,$P12*$Q12) -> 600 | V12: =IF(OR($T12="",$U12=""),0,$T12*$U12) -> 0 | Z12: =IF(OR($X12="",$Y12=""),0,$X12*$Y12) -> 0 | AA12: 0 | AB12: =$R12+$V12+$Z12 -> 600 | AC12: =IF($B12="","",$AB12+$AA12+$N12) -> 1140 | AD12: =IF(OR($K12="",$K12=0,$AC12=""),"",$AC12/$K12) -> 760 | AE12: Quarterly PM | AF12: =IFERROR(INDEX('Task Master'!$D:$D,MATCH($F12,'Task Master'!$C:$C,0)),"") -> Air_Compressor
A13: =IF(B13="","",ROW()-1) -> 12 | B13: 2026-07-10 | C13: LV-1003 | D13: =IFERROR(INDEX('Asset Register'!$B:$B,MATCH($C13,'Asset Register'!$A:$A,0)),"") -> Sedan Pool Car | E13: Light | F13: Automobile | G13: Change Spark plugs | H13: =IFERROR(INDEX('Task Master'!$E:$E,MATCH($F13&"||"&$G13,'Task Master'!$K:$K,0)),"") -> III. General Service C = 20,000 KM | I13: =IFERROR(INDEX('Task Master'!$F:$F,MATCH($F13&"||"&$G13,'Task Master'!$K:$K,0)),"") -> Preventive | J13: =IFERROR(INDEX('Task Master'!$H:$H,MATCH($F13&"||"&$G13,'Task Master'!$K:$K,0)),"") -> 1 | K13: 1 | L13: 1 | M13: 150 | N13: =IF(OR($K13="",$L13="",$M13=""),"",$K13*$L13*$M13) -> 150 | O13: Spark plug set (4) | P13: 4 | Q13: 75 | R13: =IF(OR($P13="",$Q13=""),0,$P13*$Q13) -> 300 | V13: =IF(OR($T13="",$U13=""),0,$T13*$U13) -> 0 | Z13: =IF(OR($X13="",$Y13=""),0,$X13*$Y13) -> 0 | AA13: 0 | AB13: =$R13+$V13+$Z13 -> 300 | AC13: =IF($B13="","",$AB13+$AA13+$N13) -> 450 | AD13: =IF(OR($K13="",$K13=0,$AC13=""),"",$AC13/$K13) -> 450 | AE13: Minor tune-up | AF13: =IFERROR(INDEX('Task Master'!$D:$D,MATCH($F13,'Task Master'!$C:$C,0)),"") -> Automobile
A14: =IF(B14="","",ROW()-1) -> 13 | B14: 2026-07-10 | C14: AA-65266 | D14: =IFERROR(INDEX('Asset Register'!$B:$B,MATCH($C14,'Asset Register'!$A:$A,0)),"") -> Bull Dozer (CAT) | E14: Machinery | F14: Dozer | G14: Repair (change) Sprocket (single side) | H14: =IFERROR(INDEX('Task Master'!$E:$E,MATCH($F14&"||"&$G14,'Task Master'!$K:$K,0)),"") -> I. Hydraulic and Power Train System | I14: =IFERROR(INDEX('Task Master'!$F:$F,MATCH($F14&"||"&$G14,'Task Master'!$K:$K,0)),"") -> Corrective | J14: =IFERROR(INDEX('Task Master'!$H:$H,MATCH($F14&"||"&$G14,'Task Master'!$K:$K,0)),"") -> 9 | K14: 9 | L14: 2 | M14: 250 | N14: =IF(OR($K14="",$L14="",$M14=""),"",$K14*$L14*$M14) -> 4500 | O14: Drive sprocket | P14: 1 | Q14: 4500 | R14: =IF(OR($P14="",$Q14=""),0,$P14*$Q14) -> 4500 | V14: =IF(OR($T14="",$U14=""),0,$T14*$U14) -> 0 | Z14: =IF(OR($X14="",$Y14=""),0,$X14*$Y14) -> 0 | AA14: 0 | AB14: =$R14+$V14+$Z14 -> 4500 | AC14: =IF($B14="","",$AB14+$AA14+$N14) -> 9000 | AD14: =IF(OR($K14="",$K14=0,$AC14=""),"",$AC14/$K14) -> 1000 | AE14: Sprocket replaced | AF14: =IFERROR(INDEX('Task Master'!$D:$D,MATCH($F14,'Task Master'!$C:$C,0)),"") -> Dozer
A15: =IF(B15="","",ROW()-1) -> 14 | B15: 2026-07-10 | C15: HT-7001 | D15: =IFERROR(INDEX('Asset Register'!$B:$B,MATCH($C15,'Asset Register'!$A:$A,0)),"") -> Heavy Fuel Tanker | E15: Heavy | F15: Heavy Truck | G15: Change all Gear oil (Transmission Oil & Differential oil) | H15: =IFERROR(INDEX('Task Master'!$E:$E,MATCH($F15&"||"&$G15,'Task Master'!$K:$K,0)),"") -> III. General Service C = 20,000 KM | I15: =IFERROR(INDEX('Task Master'!$F:$F,MATCH($F15&"||"&$G15,'Task Master'!$K:$K,0)),"") -> Preventive | J15: =IFERROR(INDEX('Task Master'!$H:$H,MATCH($F15&"||"&$G15,'Task Master'!$K:$K,0)),"") -> 3 | K15: 3 | L15: 2 | M15: 220 | N15: =IF(OR($K15="",$L15="",$M15=""),"",$K15*$L15*$M15) -> 1320 | O15: Transmission oil | P15: 8 | Q15: 200 | R15: =IF(OR($P15="",$Q15=""),0,$P15*$Q15) -> 1600 | S15: Differential oil | T15: 4 | U15: 200 | V15: =IF(OR($T15="",$U15=""),0,$T15*$U15) -> 800 | Z15: =IF(OR($X15="",$Y15=""),0,$X15*$Y15) -> 0 | AA15: 200 | AB15: =$R15+$V15+$Z15 -> 2400 | AC15: =IF($B15="","",$AB15+$AA15+$N15) -> 3920 | AD15: =IF(OR($K15="",$K15=0,$AC15=""),"",$AC15/$K15) -> 1306.6667 | AE15: Full service | AF15: =IFERROR(INDEX('Task Master'!$D:$D,MATCH($F15,'Task Master'!$C:$C,0)),"") -> Heavy_Truck
A16: =IF(B16="","",ROW()-1) -> 15 | B16: 2026-07-10 | C16: EL-8001 | D16: =IFERROR(INDEX('Asset Register'!$B:$B,MATCH($C16,'Asset Register'!$A:$A,0)),"") -> Site Electrical Panel | E16: Others | F16: Electrical & Electronics | G16: Checking & Correcting battery | H16: =IFERROR(INDEX('Task Master'!$E:$E,MATCH($F16&"||"&$G16,'Task Master'!$K:$K,0)),"") -> II. Chassis Electrical Repair | I16: =IFERROR(INDEX('Task Master'!$F:$F,MATCH($F16&"||"&$G16,'Task Master'!$K:$K,0)),"") -> Corrective | J16: =IFERROR(INDEX('Task Master'!$H:$H,MATCH($F16&"||"&$G16,'Task Master'!$K:$K,0)),"") -> 1 | K16: 1 | L16: 1 | M16: 180 | N16: =IF(OR($K16="",$L16="",$M16=""),"",$K16*$L16*$M16) -> 180 | O16: Terminal cleaner & clamps | P16: 1 | Q16: 150 | R16: =IF(OR($P16="",$Q16=""),0,$P16*$Q16) -> 150 | V16: =IF(OR($T16="",$U16=""),0,$T16*$U16) -> 0 | Z16: =IF(OR($X16="",$Y16=""),0,$X16*$Y16) -> 0 | AA16: 0 | AB16: =$R16+$V16+$Z16 -> 150 | AC16: =IF($B16="","",$AB16+$AA16+$N16) -> 330 | AD16: =IF(OR($K16="",$K16=0,$AC16=""),"",$AC16/$K16) -> 330 | AE16: Battery terminals cleaned | AF16: =IFERROR(INDEX('Task Master'!$D:$D,MATCH($F16,'Task Master'!$C:$C,0)),"") -> Electrical_Electronics
A17: =IF(B17="","",ROW()-1) | D17: =IF($C17="","",IFERROR(INDEX('Asset Register'!$B:$B,MATCH($C17,'Asset Register'!$A:$A,0)),"")) | H17: =IFERROR(INDEX('Task Master'!$E:$E,MATCH($F17&"||"&$G17,'Task Master'!$K:$K,0)),"") | I17: =IFERROR(INDEX('Task Master'!$F:$F,MATCH($F17&"||"&$G17,'Task Master'!$K:$K,0)),"") | J17: =IFERROR(INDEX('Task Master'!$H:$H,MATCH($F17&"||"&$G17,'Task Master'!$K:$K,0)),"") | N17: =IF(OR($K17="",$L17="",$M17=""),"",$K17*$L17*$M17) | R17: =IF(OR($P17="",$Q17=""),0,$P17*$Q17) -> 0 | V17: =IF(OR($T17="",$U17=""),0,$T17*$U17) -> 0 | Z17: =IF(OR($X17="",$Y17=""),0,$X17*$Y17) -> 0 | AB17: =$R17+$V17+$Z17 -> 0 | AC17: =IF($B17="","",$AB17+$AA17+$N17) | AD17: =IF(OR($K17="",$K17=0,$AC17=""),"",$AC17/$K17) | AF17: =IFERROR(INDEX('Task Master'!$D:$D,MATCH($F17,'Task Master'!$C:$C,0)),"")
A18: =IF(B18="","",ROW()-1) | D18: =IF($C18="","",IFERROR(INDEX('Asset Register'!$B:$B,MATCH($C18,'Asset Register'!$A:$A,0)),"")) | H18: =IFERROR(INDEX('Task Master'!$E:$E,MATCH($F18&"||"&$G18,'Task Master'!$K:$K,0)),"") | I18: =IFERROR(INDEX('Task Master'!$F:$F,MATCH($F18&"||"&$G18,'Task Master'!$K:$K,0)),"") | J18: =IFERROR(INDEX('Task Master'!$H:$H,MATCH($F18&"||"&$G18,'Task Master'!$K:$K,0)),"") | N18: =IF(OR($K18="",$L18="",$M18=""),"",$K18*$L18*$M18) | R18: =IF(OR($P18="",$Q18=""),0,$P18*$Q18) -> 0 | V18: =IF(OR($T18="",$U18=""),0,$T18*$U18) -> 0 | Z18: =IF(OR($X18="",$Y18=""),0,$X18*$Y18) -> 0 | AB18: =$R18+$V18+$Z18 -> 0 | AC18: =IF($B18="","",$AB18+$AA18+$N18) | AD18: =IF(OR($K18="",$K18=0,$AC18=""),"",$AC18/$K18) | AF18: =IFERROR(INDEX('Task Master'!$D:$D,MATCH($F18,'Task Master'!$C:$C,0)),"")
A19: =IF(B19="","",ROW()-1) | D19: =IF($C19="","",IFERROR(INDEX('Asset Register'!$B:$B,MATCH($C19,'Asset Register'!$A:$A,0)),"")) | H19: =IFERROR(INDEX('Task Master'!$E:$E,MATCH($F19&"||"&$G19,'Task Master'!$K:$K,0)),"") | I19: =IFERROR(INDEX('Task Master'!$F:$F,MATCH($F19&"||"&$G19,'Task Master'!$K:$K,0)),"") | J19: =IFERROR(INDEX('Task Master'!$H:$H,MATCH($F19&"||"&$G19,'Task Master'!$K:$K,0)),"") | N19: =IF(OR($K19="",$L19="",$M19=""),"",$K19*$L19*$M19) | R19: =IF(OR($P19="",$Q19=""),0,$P19*$Q19) -> 0 | V19: =IF(OR($T19="",$U19=""),0,$T19*$U19) -> 0 | Z19: =IF(OR($X19="",$Y19=""),0,$X19*$Y19) -> 0 | AB19: =$R19+$V19+$Z19 -> 0 | AC19: =IF($B19="","",$AB19+$AA19+$N19) | AD19: =IF(OR($K19="",$K19=0,$AC19=""),"",$AC19/$K19) | AF19: =IFERROR(INDEX('Task Master'!$D:$D,MATCH($F19,'Task Master'!$C:$C,0)),"")
A20: =IF(B20="","",ROW()-1) | D20: =IF($C20="","",IFERROR(INDEX('Asset Register'!$B:$B,MATCH($C20,'Asset Register'!$A:$A,0)),"")) | H20: =IFERROR(INDEX('Task Master'!$E:$E,MATCH($F20&"||"&$G20,'Task Master'!$K:$K,0)),"") | I20: =IFERROR(INDEX('Task Master'!$F:$F,MATCH($F20&"||"&$G20,'Task Master'!$K:$K,0)),"") | J20: =IFERROR(INDEX('Task Master'!$H:$H,MATCH($F20&"||"&$G20,'Task Master'!$K:$K,0)),"") | N20: =IF(OR($K20="",$L20="",$M20=""),"",$K20*$L20*$M20) | R20: =IF(OR($P20="",$Q20=""),0,$P20*$Q20) -> 0 | V20: =IF(OR($T20="",$U20=""),0,$T20*$U20) -> 0 | Z20: =IF(OR($X20="",$Y20=""),0,$X20*$Y20) -> 0 | AB20: =$R20+$V20+$Z20 -> 0 | AC20: =IF($B20="","",$AB20+$AA20+$N20) | AD20: =IF(OR($K20="",$K20=0,$AC20=""),"",$AC20/$K20) | AF20: =IFERROR(INDEX('Task Master'!$D:$D,MATCH($F20,'Task Master'!$C:$C,0)),"")
A21: =IF(B21="","",ROW()-1) | D21: =IF($C21="","",IFERROR(INDEX('Asset Register'!$B:$B,MATCH($C21,'Asset Register'!$A:$A,0)),"")) | H21: =IFERROR(INDEX('Task Master'!$E:$E,MATCH($F21&"||"&$G21,'Task Master'!$K:$K,0)),"") | I21: =IFERROR(INDEX('Task Master'!$F:$F,MATCH($F21&"||"&$G21,'Task Master'!$K:$K,0)),"") | J21: =IFERROR(INDEX('Task Master'!$H:$H,MATCH($F21&"||"&$G21,'Task Master'!$K:$K,0)),"") | N21: =IF(OR($K21="",$L21="",$M21=""),"",$K21*$L21*$M21) | R21: =IF(OR($P21="",$Q21=""),0,$P21*$Q21) -> 0 | V21: =IF(OR($T21="",$U21=""),0,$T21*$U21) -> 0 | Z21: =IF(OR($X21="",$Y21=""),0,$X21*$Y21) -> 0 | AB21: =$R21+$V21+$Z21 -> 0 | AC21: =IF($B21="","",$AB21+$AA21+$N21) | AD21: =IF(OR($K21="",$K21=0,$AC21=""),"",$AC21/$K21) | AF21: =IFERROR(INDEX('Task Master'!$D:$D,MATCH($F21,'Task Master'!$C:$C,0)),"")
A22: =IF(B22="","",ROW()-1) | D22: =IF($C22="","",IFERROR(INDEX('Asset Register'!$B:$B,MATCH($C22,'Asset Register'!$A:$A,0)),"")) | H22: =IFERROR(INDEX('Task Master'!$E:$E,MATCH($F22&"||"&$G22,'Task Master'!$K:$K,0)),"") | I22: =IFERROR(INDEX('Task Master'!$F:$F,MATCH($F22&"||"&$G22,'Task Master'!$K:$K,0)),"") | J22: =IFERROR(INDEX('Task Master'!$H:$H,MATCH($F22&"||"&$G22,'Task Master'!$K:$K,0)),"") | N22: =IF(OR($K22="",$L22="",$M22=""),"",$K22*$L22*$M22) | R22: =IF(OR($P22="",$Q22=""),0,$P22*$Q22) -> 0 | V22: =IF(OR($T22="",$U22=""),0,$T22*$U22) -> 0 | Z22: =IF(OR($X22="",$Y22=""),0,$X22*$Y22) -> 0 | AB22: =$R22+$V22+$Z22 -> 0 | AC22: =IF($B22="","",$AB22+$AA22+$N22) | AD22: =IF(OR($K22="",$K22=0,$AC22=""),"",$AC22/$K22) | AF22: =IFERROR(INDEX('Task Master'!$D:$D,MATCH($F22,'Task Master'!$C:$C,0)),"")
A23: =IF(B23="","",ROW()-1) | D23: =IF($C23="","",IFERROR(INDEX('Asset Register'!$B:$B,MATCH($C23,'Asset Register'!$A:$A,0)),"")) | H23: =IFERROR(INDEX('Task Master'!$E:$E,MATCH($F23&"||"&$G23,'Task Master'!$K:$K,0)),"") | I23: =IFERROR(INDEX('Task Master'!$F:$F,MATCH($F23&"||"&$G23,'Task Master'!$K:$K,0)),"") | J23: =IFERROR(INDEX('Task Master'!$H:$H,MATCH($F23&"||"&$G23,'Task Master'!$K:$K,0)),"") | N23: =IF(OR($K23="",$L23="",$M23=""),"",$K23*$L23*$M23) | R23: =IF(OR($P23="",$Q23=""),0,$P23*$Q23) -> 0 | V23: =IF(OR($T23="",$U23=""),0,$T23*$U23) -> 0 | Z23: =IF(OR($X23="",$Y23=""),0,$X23*$Y23) -> 0 | AB23: =$R23+$V23+$Z23 -> 0 | AC23: =IF($B23="","",$AB23+$AA23+$N23) | AD23: =IF(OR($K23="",$K23=0,$AC23=""),"",$AC23/$K23) | AF23: =IFERROR(INDEX('Task Master'!$D:$D,MATCH($F23,'Task Master'!$C:$C,0)),"")
A24: =IF(B24="","",ROW()-1) | D24: =IF($C24="","",IFERROR(INDEX('Asset Register'!$B:$B,MATCH($C24,'Asset Register'!$A:$A,0)),"")) | H24: =IFERROR(INDEX('Task Master'!$E:$E,MATCH($F24&"||"&$G24,'Task Master'!$K:$K,0)),"") | I24: =IFERROR(INDEX('Task Master'!$F:$F,MATCH($F24&"||"&$G24,'Task Master'!$K:$K,0)),"") | J24: =IFERROR(INDEX('Task Master'!$H:$H,MATCH($F24&"||"&$G24,'Task Master'!$K:$K,0)),"") | N24: =IF(OR($K24="",$L24="",$M24=""),"",$K24*$L24*$M24) | R24: =IF(OR($P24="",$Q24=""),0,$P24*$Q24) -> 0 | V24: =IF(OR($T24="",$U24=""),0,$T24*$U24) -> 0 | Z24: =IF(OR($X24="",$Y24=""),0,$X24*$Y24) -> 0 | AB24: =$R24+$V24+$Z24 -> 0 | AC24: =IF($B24="","",$AB24+$AA24+$N24) | AD24: =IF(OR($K24="",$K24=0,$AC24=""),"",$AC24/$K24) | AF24: =IFERROR(INDEX('Task Master'!$D:$D,MATCH($F24,'Task Master'!$C:$C,0)),"")
A25: =IF(B25="","",ROW()-1) | D25: =IF($C25="","",IFERROR(INDEX('Asset Register'!$B:$B,MATCH($C25,'Asset Register'!$A:$A,0)),"")) | H25: =IFERROR(INDEX('Task Master'!$E:$E,MATCH($F25&"||"&$G25,'Task Master'!$K:$K,0)),"") | I25: =IFERROR(INDEX('Task Master'!$F:$F,MATCH($F25&"||"&$G25,'Task Master'!$K:$K,0)),"") | J25: =IFERROR(INDEX('Task Master'!$H:$H,MATCH($F25&"||"&$G25,'Task Master'!$K:$K,0)),"") | N25: =IF(OR($K25="",$L25="",$M25=""),"",$K25*$L25*$M25) | R25: =IF(OR($P25="",$Q25=""),0,$P25*$Q25) -> 0 | V25: =IF(OR($T25="",$U25=""),0,$T25*$U25) -> 0 | Z25: =IF(OR($X25="",$Y25=""),0,$X25*$Y25) -> 0 | AB25: =$R25+$V25+$Z25 -> 0 | AC25: =IF($B25="","",$AB25+$AA25+$N25) | AD25: =IF(OR($K25="",$K25=0,$AC25=""),"",$AC25/$K25) | AF25: =IFERROR(INDEX('Task Master'!$D:$D,MATCH($F25,'Task Master'!$C:$C,0)),"")
A26: =IF(B26="","",ROW()-1) | D26: =IF($C26="","",IFERROR(INDEX('Asset Register'!$B:$B,MATCH($C26,'Asset Register'!$A:$A,0)),"")) | H26: =IFERROR(INDEX('Task Master'!$E:$E,MATCH($F26&"||"&$G26,'Task Master'!$K:$K,0)),"") | I26: =IFERROR(INDEX('Task Master'!$F:$F,MATCH($F26&"||"&$G26,'Task Master'!$K:$K,0)),"") | J26: =IFERROR(INDEX('Task Master'!$H:$H,MATCH($F26&"||"&$G26,'Task Master'!$K:$K,0)),"") | N26: =IF(OR($K26="",$L26="",$M26=""),"",$K26*$L26*$M26) | R26: =IF(OR($P26="",$Q26=""),0,$P26*$Q26) -> 0 | V26: =IF(OR($T26="",$U26=""),0,$T26*$U26) -> 0 | Z26: =IF(OR($X26="",$Y26=""),0,$X26*$Y26) -> 0 | AB26: =$R26+$V26+$Z26 -> 0 | AC26: =IF($B26="","",$AB26+$AA26+$N26) | AD26: =IF(OR($K26="",$K26=0,$AC26=""),"",$AC26/$K26) | AF26: =IFERROR(INDEX('Task Master'!$D:$D,MATCH($F26,'Task Master'!$C:$C,0)),"")
A27: =IF(B27="","",ROW()-1) | D27: =IF($C27="","",IFERROR(INDEX('Asset Register'!$B:$B,MATCH($C27,'Asset Register'!$A:$A,0)),"")) | H27: =IFERROR(INDEX('Task Master'!$E:$E,MATCH($F27&"||"&$G27,'Task Master'!$K:$K,0)),"") | I27: =IFERROR(INDEX('Task Master'!$F:$F,MATCH($F27&"||"&$G27,'Task Master'!$K:$K,0)),"") | J27: =IFERROR(INDEX('Task Master'!$H:$H,MATCH($F27&"||"&$G27,'Task Master'!$K:$K,0)),"") | N27: =IF(OR($K27="",$L27="",$M27=""),"",$K27*$L27*$M27) | R27: =IF(OR($P27="",$Q27=""),0,$P27*$Q27) -> 0 | V27: =IF(OR($T27="",$U27=""),0,$T27*$U27) -> 0 | Z27: =IF(OR($X27="",$Y27=""),0,$X27*$Y27) -> 0 | AB27: =$R27+$V27+$Z27 -> 0 | AC27: =IF($B27="","",$AB27+$AA27+$N27) | AD27: =IF(OR($K27="",$K27=0,$AC27=""),"",$AC27/$K27) | AF27: =IFERROR(INDEX('Task Master'!$D:$D,MATCH($F27,'Task Master'!$C:$C,0)),"")
A28: =IF(B28="","",ROW()-1) | D28: =IF($C28="","",IFERROR(INDEX('Asset Register'!$B:$B,MATCH($C28,'Asset Register'!$A:$A,0)),"")) | H28: =IFERROR(INDEX('Task Master'!$E:$E,MATCH($F28&"||"&$G28,'Task Master'!$K:$K,0)),"") | I28: =IFERROR(INDEX('Task Master'!$F:$F,MATCH($F28&"||"&$G28,'Task Master'!$K:$K,0)),"") | J28: =IFERROR(INDEX('Task Master'!$H:$H,MATCH($F28&"||"&$G28,'Task Master'!$K:$K,0)),"") | N28: =IF(OR($K28="",$L28="",$M28=""),"",$K28*$L28*$M28) | R28: =IF(OR($P28="",$Q28=""),0,$P28*$Q28) -> 0 | V28: =IF(OR($T28="",$U28=""),0,$T28*$U28) -> 0 | Z28: =IF(OR($X28="",$Y28=""),0,$X28*$Y28) -> 0 | AB28: =$R28+$V28+$Z28 -> 0 | AC28: =IF($B28="","",$AB28+$AA28+$N28) | AD28: =IF(OR($K28="",$K28=0,$AC28=""),"",$AC28/$K28) | AF28: =IFERROR(INDEX('Task Master'!$D:$D,MATCH($F28,'Task Master'!$C:$C,0)),"")
... A1000: =IF(B1000="","",ROW()-1) | D1000: =IF($C1000="","",IFERROR(INDEX('Asset Register'!$B:$B,MATCH($C1000,'Asset Register'!$A:$A,0)),"")) | H1000: =IFERROR(INDEX('Task Master'!$E:$E,MATCH($F1000&"||"&$G1000,'Task Master'!$K:$K,0)),"") | I1000: =IFERROR(INDEX('Task Master'!$F:$F,MATCH($F1000&"||"&$G1000,'Task Master'!$K:$K,0)),"") | J1000: =IFERROR(INDEX('Task Master'!$H:$H,MATCH($F1000&"||"&$G1000,'Task Master'!$K:$K,0)),"") | N1000: =IF(OR($K1000="",$L1000="",$M1000=""),"",$K1000*$L1000*$M1000) | R1000: =IF(OR($P1000="",$Q1000=""),0,$P1000*$Q1000) -> 0 | V1000: =IF(OR($T1000="",$U1000=""),0,$T1000*$U1000) -> 0 | Z1000: =IF(OR($X1000="",$Y1000=""),0,$X1000*$Y1000) -> 0 | AB1000: =$R1000+$V1000+$Z1000 -> 0 | AC1000: =IF($B1000="","",$AB1000+$AA1000+$N1000) | AD1000: =IF(OR($K1000="",$K1000=0,$AC1000=""),"",$AC1000/$K1000) | AF1000: =IFERROR(INDEX('Task Master'!$D:$D,MATCH($F1000,'Task Master'!$C:$C,0)),"")

Sheet Dashboard
B2: 🚜 FLEET MAINTENANCE & FINANCIAL DASHBOARD
B4: ="Assets: "&COUNTA('Asset Register'!A2:A200)&" | Operations logged: "&COUNT('Daily Operations Log'!A2:A500)&" | Maintenance events: "&COUNT('Maintenance Log'!A2:A1000)&" | Updated live from source sheets" -> Assets: 15 | Operations logged: 15 | Maintenance events: 15 | Updated live from source sheets
B7: 🚜 FLEET SIZE | D7: ✅ AVG AVAILABILITY | F7: ⚙️ AVG UTILIZATION | H7: ⏱️ TOTAL DOWNTIME (Hr) | J7: ⚠️ CRITICAL ENTRIES
B8: =COUNTA('Asset Register'!A2:A200) -> 15 | D8: =IFERROR(AVERAGE('Daily Operations Log'!J2:J500),0) -> 0.90873016 | F8: =IFERROR(AVERAGE('Daily Operations Log'!K2:K500),0) -> 0.77075397 | H8: =SUM('Daily Operations Log'!I2:I500) -> 10.5 | J8: =COUNTIFS('Daily Operations Log'!L2:L500,">0.3") -> 1
B11: 💰 TOTAL REVENUE (ETB) | D11: 🔧 TOTAL MAINT. COST (ETB) | F11: 📈 NET OPERATING RESULT (ETB) | H11: ⛽ TOTAL FUEL (L) | J11: 📊 FUEL VARIANCE vs NORM
B12: =SUM('Daily Operations Log'!U2:U500) -> 100050 | D12: =SUM('Maintenance Log'!AC2:AC1000) -> 156175 | F12: =B12-D12 -> -56125 | H12: =SUM('Daily Operations Log'!P2:P500) -> 1550 | J12: =IFERROR((SUM('Daily Operations Log'!P2:P500)-SUM('Daily Operations Log'!Q2:Q500))/SUM('Daily Operations Log'!Q2:Q500),0) -> 0.045178692
B14: 📊 1. PRODUCTIVITY OVERVIEW — AVAILABILITY & UTILIZATION BY ASSET
B16: Asset ID | C16: Asset Name | D16: Equipment Type | E16: Total Operable Hr | F16: Total Idle Hr | G16: Total Down Hr | H16: Avg Availability % | I16: Avg Utilization % | J16: Idle % (of Operable)
B17: ='Asset Register'!A2 -> AA-65266 | C17: ='Asset Register'!B2 -> Bull Dozer (CAT) | D17: ='Asset Register'!D2 -> Dozer | E17: =SUMIFS('Daily Operations Log'!$G$2:$G$500,'Daily Operations Log'!$C$2:$C$500,$B17) -> 5.5 | F17: =SUMIFS('Daily Operations Log'!$H$2:$H$500,'Daily Operations Log'!$C$2:$C$500,$B17) -> 2 | G17: =SUMIFS('Daily Operations Log'!$I$2:$I$500,'Daily Operations Log'!$C$2:$C$500,$B17) -> 0.5 | H17: =IFERROR(AVERAGEIFS('Daily Operations Log'!$J$2:$J$500,'Daily Operations Log'!$C$2:$C$500,$B17),"") -> 0.91666667 | I17: =IFERROR(AVERAGEIFS('Daily Operations Log'!$K$2:$K$500,'Daily Operations Log'!$C$2:$C$500,$B17),"") -> 0.6875 | J17: =IFERROR($F17/$E17,"") -> 0.36363636
B18: ='Asset Register'!A3 -> AA-65265 | C18: ='Asset Register'!B3 -> Bull Dozer (CAT) | D18: ='Asset Register'!D3 -> Dozer | E18: =SUMIFS('Daily Operations Log'!$G$2:$G$500,'Daily Operations Log'!$C$2:$C$500,$B18) -> 0 | F18: =SUMIFS('Daily Operations Log'!$H$2:$H$500,'Daily Operations Log'!$C$2:$C$500,$B18) -> 0 | G18: =SUMIFS('Daily Operations Log'!$I$2:$I$500,'Daily Operations Log'!$C$2:$C$500,$B18) -> 8 | H18: =IFERROR(AVERAGEIFS('Daily Operations Log'!$J$2:$J$500,'Daily Operations Log'!$C$2:$C$500,$B18),"") -> 0 | I18: =IFERROR(AVERAGEIFS('Daily Operations Log'!$K$2:$K$500,'Daily Operations Log'!$C$2:$C$500,$B18),"") -> 0 | J18: =IFERROR($F18/$E18,"")
B19: ='Asset Register'!A4 -> AA-60042 | C19: ='Asset Register'!B4 -> Bull Dozer (Komatsu) | D19: ='Asset Register'!D4 -> Dozer | E19: =SUMIFS('Daily Operations Log'!$G$2:$G$500,'Daily Operations Log'!$C$2:$C$500,$B19) -> 4 | F19: =SUMIFS('Daily Operations Log'!$H$2:$H$500,'Daily Operations Log'!$C$2:$C$500,$B19) -> 4 | G19: =SUMIFS('Daily Operations Log'!$I$2:$I$500,'Daily Operations Log'!$C$2:$C$500,$B19) -> 0 | H19: =IFERROR(AVERAGEIFS('Daily Operations Log'!$J$2:$J$500,'Daily Operations Log'!$C$2:$C$500,$B19),"") -> 1 | I19: =IFERROR(AVERAGEIFS('Daily Operations Log'!$K$2:$K$500,'Daily Operations Log'!$C$2:$C$500,$B19),"") -> 0.5 | J19: =IFERROR($F19/$E19,"") -> 1
B20: ='Asset Register'!A5 -> AA-65585 | C20: ='Asset Register'!B5 -> Dump Truck (Volvo) | D20: ='Asset Register'!D5 -> Heavy Truck | E20: =SUMIFS('Daily Operations Log'!$G$2:$G$500,'Daily Operations Log'!$C$2:$C$500,$B20) -> 6.5 | F20: =SUMIFS('Daily Operations Log'!$H$2:$H$500,'Daily Operations Log'!$C$2:$C$500,$B20) -> 1.5 | G20: =SUMIFS('Daily Operations Log'!$I$2:$I$500,'Daily Operations Log'!$C$2:$C$500,$B20) -> 0 | H20: =IFERROR(AVERAGEIFS('Daily Operations Log'!$J$2:$J$500,'Daily Operations Log'!$C$2:$C$500,$B20),"") -> 1 | I20: =IFERROR(AVERAGEIFS('Daily Operations Log'!$K$2:$K$500,'Daily Operations Log'!$C$2:$C$500,$B20),"") -> 0.8125 | J20: =IFERROR($F20/$E20,"") -> 0.23076923
B21: ='Asset Register'!A6 -> AA-9018 | C21: ='Asset Register'!B6 -> Bull Dozer (CAT) | D21: ='Asset Register'!D6 -> Dozer | E21: =SUMIFS('Daily Operations Log'!$G$2:$G$500,'Daily Operations Log'!$C$2:$C$500,$B21) -> 5 | F21: =SUMIFS('Daily Operations Log'!$H$2:$H$500,'Daily Operations Log'!$C$2:$C$500,$B21) -> 1 | G21: =SUMIFS('Daily Operations Log'!$I$2:$I$500,'Daily Operations Log'!$C$2:$C$500,$B21) -> 2 | H21: =IFERROR(AVERAGEIFS('Daily Operations Log'!$J$2:$J$500,'Daily Operations Log'!$C$2:$C$500,$B21),"") -> 0.71428571 | I21: =IFERROR(AVERAGEIFS('Daily Operations Log'!$K$2:$K$500,'Daily Operations Log'!$C$2:$C$500,$B21),"") -> 0.625 | J21: =IFERROR($F21/$E21,"") -> 0.2
B22: ='Asset Register'!A7 -> LV-1001 | C22: ='Asset Register'!B7 -> Toyota Land Cruiser | D22: ='Asset Register'!D7 -> Automobile | E22: =SUMIFS('Daily Operations Log'!$G$2:$G$500,'Daily Operations Log'!$C$2:$C$500,$B22) -> 6 | F22: =SUMIFS('Daily Operations Log'!$H$2:$H$500,'Daily Operations Log'!$C$2:$C$500,$B22) -> 1 | G22: =SUMIFS('Daily Operations Log'!$I$2:$I$500,'Daily Operations Log'!$C$2:$C$500,$B22) -> 0 | H22: =IFERROR(AVERAGEIFS('Daily Operations Log'!$J$2:$J$500,'Daily Operations Log'!$C$2:$C$500,$B22),"") -> 1 | I22: =IFERROR(AVERAGEIFS('Daily Operations Log'!$K$2:$K$500,'Daily Operations Log'!$C$2:$C$500,$B22),"") -> 0.85714286 | J22: =IFERROR($F22/$E22,"") -> 0.16666667
B23: ='Asset Register'!A8 -> LV-1002 | C23: ='Asset Register'!B8 -> Toyota Hilux Pickup | D23: ='Asset Register'!D8 -> Pick Up / Station Wagon / Mini Bus | E23: =SUMIFS('Daily Operations Log'!$G$2:$G$500,'Daily Operations Log'!$C$2:$C$500,$B23) -> 7 | F23: =SUMIFS('Daily Operations Log'!$H$2:$H$500,'Daily Operations Log'!$C$2:$C$500,$B23) -> 0.5 | G23: =SUMIFS('Daily Operations Log'!$I$2:$I$500,'Daily Operations Log'!$C$2:$C$500,$B23) -> 0 | H23: =IFERROR(AVERAGEIFS('Daily Operations Log'!$J$2:$J$500,'Daily Operations Log'!$C$2:$C$500,$B23),"") -> 1 | I23: =IFERROR(AVERAGEIFS('Daily Operations Log'!$K$2:$K$500,'Daily Operations Log'!$C$2:$C$500,$B23),"") -> 0.93333333 | J23: =IFERROR($F23/$E23,"") -> 0.071428571
B24: ='Asset Register'!A9 -> LV-1003 | C24: ='Asset Register'!B9 -> Sedan Pool Car | D24: ='Asset Register'!D9 -> Automobile | E24: =SUMIFS('Daily Operations Log'!$G$2:$G$500,'Daily Operations Log'!$C$2:$C$500,$B24) -> 5 | F24: =SUMIFS('Daily Operations Log'!$H$2:$H$500,'Daily Operations Log'!$C$2:$C$500,$B24) -> 1 | G24: =SUMIFS('Daily Operations Log'!$I$2:$I$500,'Daily Operations Log'!$C$2:$C$500,$B24) -> 0 | H24: =IFERROR(AVERAGEIFS('Daily Operations Log'!$J$2:$J$500,'Daily Operations Log'!$C$2:$C$500,$B24),"") -> 1 | I24: =IFERROR(AVERAGEIFS('Daily Operations Log'!$K$2:$K$500,'Daily Operations Log'!$C$2:$C$500,$B24),"") -> 0.83333333 | J24: =IFERROR($F24/$E24,"") -> 0.2
B25: ='Asset Register'!A10 -> EX-2001 | C25: ='Asset Register'!B10 -> Excavator (Komatsu PC200) | D25: ='Asset Register'!D10 -> Excavator | E25: =SUMIFS('Daily Operations Log'!$G$2:$G$500,'Daily Operations Log'!$C$2:$C$500,$B25) -> 7 | F25: =SUMIFS('Daily Operations Log'!$H$2:$H$500,'Daily Operations Log'!$C$2:$C$500,$B25) -> 1 | G25: =SUMIFS('Daily Operations Log'!$I$2:$I$500,'Daily Operations Log'!$C$2:$C$500,$B25) -> 0 | H25: =IFERROR(AVERAGEIFS('Daily Operations Log'!$J$2:$J$500,'Daily Operations Log'!$C$2:$C$500,$B25),"") -> 1 | I25: =IFERROR(AVERAGEIFS('Daily Operations Log'!$K$2:$K$500,'Daily Operations Log'!$C$2:$C$500,$B25),"") -> 0.875 | J25: =IFERROR($F25/$E25,"") -> 0.14285714
B26: ='Asset Register'!A11 -> GD-3001 | C26: ='Asset Register'!B11 -> Grader (CAT 140K) | D26: ='Asset Register'!D11 -> Grader | E26: =SUMIFS('Daily Operations Log'!$G$2:$G$500,'Daily Operations Log'!$C$2:$C$500,$B26) -> 6 | F26: =SUMIFS('Daily Operations Log'!$H$2:$H$500,'Daily Operations Log'!$C$2:$C$500,$B26) -> 2 | G26: =SUMIFS('Daily Operations Log'!$I$2:$I$500,'Daily Operations Log'!$C$2:$C$500,$B26) -> 0 | H26: =IFERROR(AVERAGEIFS('Daily Operations Log'!$J$2:$J$500,'Daily Operations Log'!$C$2:$C$500,$B26),"") -> 1 | I26: =IFERROR(AVERAGEIFS('Daily Operations Log'!$K$2:$K$500,'Daily Operations Log'!$C$2:$C$500,$B26),"") -> 0.75 | J26: =IFERROR($F26/$E26,"") -> 0.33333333
B27: ='Asset Register'!A12 -> LD-4001 | C27: ='Asset Register'!B12 -> Wheel Loader (CAT 950) | D27: ='Asset Register'!D12 -> Loader | E27: =SUMIFS('Daily Operations Log'!$G$2:$G$500,'Daily Operations Log'!$C$2:$C$500,$B27) -> 6.5 | F27: =SUMIFS('Daily Operations Log'!$H$2:$H$500,'Daily Operations Log'!$C$2:$C$500,$B27) -> 1.5 | G27: =SUMIFS('Daily Operations Log'!$I$2:$I$500,'Daily Operations Log'!$C$2:$C$500,$B27) -> 0 | H27: =IFERROR(AVERAGEIFS('Daily Operations Log'!$J$2:$J$500,'Daily Operations Log'!$C$2:$C$500,$B27),"") -> 1 | I27: =IFERROR(AVERAGEIFS('Daily Operations Log'!$K$2:$K$500,'Daily Operations Log'!$C$2:$C$500,$B27),"") -> 0.8125 | J27: =IFERROR($F27/$E27,"") -> 0.23076923
B28: ='Asset Register'!A13 -> GN-5001 | C28: ='Asset Register'!B13 -> Standby Generator 150KVA | D28: ='Asset Register'!D13 -> Generator | E28: =SUMIFS('Daily Operations Log'!$G$2:$G$500,'Daily Operations Log'!$C$2:$C$500,$B28) -> 8 | F28: =SUMIFS('Daily Operations Log'!$H$2:$H$500,'Daily Operations Log'!$C$2:$C$500,$B28) -> 0 | G28: =SUMIFS('Daily Operations Log'!$I$2:$I$500,'Daily Operations Log'!$C$2:$C$500,$B28) -> 0 | H28: =IFERROR(AVERAGEIFS('Daily Operations Log'!$J$2:$J$500,'Daily Operations Log'!$C$2:$C$500,$B28),"") -> 1 | I28: =IFERROR(AVERAGEIFS('Daily Operations Log'!$K$2:$K$500,'Daily Operations Log'!$C$2:$C$500,$B28),"") -> 1 | J28: =IFERROR($F28/$E28,"") -> 0
... B31: ='Asset Register'!A16 -> EL-8001 | C31: ='Asset Register'!B16 -> Site Electrical Panel | D31: ='Asset Register'!D16 -> Electrical & Electronics | E31: =SUMIFS('Daily Operations Log'!$G$2:$G$500,'Daily Operations Log'!$C$2:$C$500,$B31) -> 8 | F31: =SUMIFS('Daily Operations Log'!$H$2:$H$500,'Daily Operations Log'!$C$2:$C$500,$B31) -> 0 | G31: =SUMIFS('Daily Operations Log'!$I$2:$I$500,'Daily Operations Log'!$C$2:$C$500,$B31) -> 0 | H31: =IFERROR(AVERAGEIFS('Daily Operations Log'!$J$2:$J$500,'Daily Operations Log'!$C$2:$C$500,$B31),"") -> 1 | I31: =IFERROR(AVERAGEIFS('Daily Operations Log'!$K$2:$K$500,'Daily Operations Log'!$C$2:$C$500,$B31),"") -> 1 | J31: =IFERROR($F31/$E31,"") -> 0
B34: 🛠️ 2. DOWNTIME ANALYSIS BY ASSET
B36: Asset ID | C36: Total Down Hr | D36: Down % | E36: Status
B37: ='Asset Register'!A2 -> AA-65266 | C37: =SUMIFS('Daily Operations Log'!$I$2:$I$500,'Daily Operations Log'!$C$2:$C$500,$B37) -> 0.5 | D37: =IFERROR($C37/(SUMIFS('Daily Operations Log'!$G$2:$G$500,'Daily Operations Log'!$C$2:$C$500,$B37)+$C37),0) -> 0.083333333 | E37: =IF($D37>0.3,"Critical",IF($D37>0,"Watch","Healthy")) -> Watch
B38: ='Asset Register'!A3 -> AA-65265 | C38: =SUMIFS('Daily Operations Log'!$I$2:$I$500,'Daily Operations Log'!$C$2:$C$500,$B38) -> 8 | D38: =IFERROR($C38/(SUMIFS('Daily Operations Log'!$G$2:$G$500,'Daily Operations Log'!$C$2:$C$500,$B38)+$C38),0) -> 1 | E38: =IF($D38>0.3,"Critical",IF($D38>0,"Watch","Healthy")) -> Critical
B39: ='Asset Register'!A4 -> AA-60042 | C39: =SUMIFS('Daily Operations Log'!$I$2:$I$500,'Daily Operations Log'!$C$2:$C$500,$B39) -> 0 | D39: =IFERROR($C39/(SUMIFS('Daily Operations Log'!$G$2:$G$500,'Daily Operations Log'!$C$2:$C$500,$B39)+$C39),0) -> 0 | E39: =IF($D39>0.3,"Critical",IF($D39>0,"Watch","Healthy")) -> Healthy
B40: ='Asset Register'!A5 -> AA-65585 | C40: =SUMIFS('Daily Operations Log'!$I$2:$I$500,'Daily Operations Log'!$C$2:$C$500,$B40) -> 0 | D40: =IFERROR($C40/(SUMIFS('Daily Operations Log'!$G$2:$G$500,'Daily Operations Log'!$C$2:$C$500,$B40)+$C40),0) -> 0 | E40: =IF($D40>0.3,"Critical",IF($D40>0,"Watch","Healthy")) -> Healthy
B41: ='Asset Register'!A6 -> AA-9018 | C41: =SUMIFS('Daily Operations Log'!$I$2:$I$500,'Daily Operations Log'!$C$2:$C$500,$B41) -> 2 | D41: =IFERROR($C41/(SUMIFS('Daily Operations Log'!$G$2:$G$500,'Daily Operations Log'!$C$2:$C$500,$B41)+$C41),0) -> 0.28571429 | E41: =IF($D41>0.3,"Critical",IF($D41>0,"Watch","Healthy")) -> Watch
B42: ='Asset Register'!A7 -> LV-1001 | C42: =SUMIFS('Daily Operations Log'!$I$2:$I$500,'Daily Operations Log'!$C$2:$C$500,$B42) -> 0 | D42: =IFERROR($C42/(SUMIFS('Daily Operations Log'!$G$2:$G$500,'Daily Operations Log'!$C$2:$C$500,$B42)+$C42),0) -> 0 | E42: =IF($D42>0.3,"Critical",IF($D42>0,"Watch","Healthy")) -> Healthy
B43: ='Asset Register'!A8 -> LV-1002 | C43: =SUMIFS('Daily Operations Log'!$I$2:$I$500,'Daily Operations Log'!$C$2:$C$500,$B43) -> 0 | D43: =IFERROR($C43/(SUMIFS('Daily Operations Log'!$G$2:$G$500,'Daily Operations Log'!$C$2:$C$500,$B43)+$C43),0) -> 0 | E43: =IF($D43>0.3,"Critical",IF($D43>0,"Watch","Healthy")) -> Healthy
B44: ='Asset Register'!A9 -> LV-1003 | C44: =SUMIFS('Daily Operations Log'!$I$2:$I$500,'Daily Operations Log'!$C$2:$C$500,$B44) -> 0 | D44: =IFERROR($C44/(SUMIFS('Daily Operations Log'!$G$2:$G$500,'Daily Operations Log'!$C$2:$C$500,$B44)+$C44),0) -> 0 | E44: =IF($D44>0.3,"Critical",IF($D44>0,"Watch","Healthy")) -> Healthy
B45: ='Asset Register'!A10 -> EX-2001 | C45: =SUMIFS('Daily Operations Log'!$I$2:$I$500,'Daily Operations Log'!$C$2:$C$500,$B45) -> 0 | D45: =IFERROR($C45/(SUMIFS('Daily Operations Log'!$G$2:$G$500,'Daily Operations Log'!$C$2:$C$500,$B45)+$C45),0) -> 0 | E45: =IF($D45>0.3,"Critical",IF($D45>0,"Watch","Healthy")) -> Healthy
B46: ='Asset Register'!A11 -> GD-3001 | C46: =SUMIFS('Daily Operations Log'!$I$2:$I$500,'Daily Operations Log'!$C$2:$C$500,$B46) -> 0 | D46: =IFERROR($C46/(SUMIFS('Daily Operations Log'!$G$2:$G$500,'Daily Operations Log'!$C$2:$C$500,$B46)+$C46),0) -> 0 | E46: =IF($D46>0.3,"Critical",IF($D46>0,"Watch","Healthy")) -> Healthy
B47: ='Asset Register'!A12 -> LD-4001 | C47: =SUMIFS('Daily Operations Log'!$I$2:$I$500,'Daily Operations Log'!$C$2:$C$500,$B47) -> 0 | D47: =IFERROR($C47/(SUMIFS('Daily Operations Log'!$G$2:$G$500,'Daily Operations Log'!$C$2:$C$500,$B47)+$C47),0) -> 0 | E47: =IF($D47>0.3,"Critical",IF($D47>0,"Watch","Healthy")) -> Healthy
B48: ='Asset Register'!A13 -> GN-5001 | C48: =SUMIFS('Daily Operations Log'!$I$2:$I$500,'Daily Operations Log'!$C$2:$C$500,$B48) -> 0 | D48: =IFERROR($C48/(SUMIFS('Daily Operations Log'!$G$2:$G$500,'Daily Operations Log'!$C$2:$C$500,$B48)+$C48),0) -> 0 | E48: =IF($D48>0.3,"Critical",IF($D48>0,"Watch","Healthy")) -> Healthy
... B51: ='Asset Register'!A16 -> EL-8001 | C51: =SUMIFS('Daily Operations Log'!$I$2:$I$500,'Daily Operations Log'!$C$2:$C$500,$B51) -> 0 | D51: =IFERROR($C51/(SUMIFS('Daily Operations Log'!$G$2:$G$500,'Daily Operations Log'!$C$2:$C$500,$B51)+$C51),0) -> 0 | E51: =IF($D51>0.3,"Critical",IF($D51>0,"Watch","Healthy")) -> Healthy
B54: 🔩 3. MAINTENANCE TREND — BY MAINTENANCE TYPE & GROUP
B56: Maintenance Type | C56: Job Count | D56: Total Time (Hrs) | E56: Total Cost (ETB)
B57: Preventive | C57: =COUNTIFS('Maintenance Log'!$I$2:$I$1000,$B57) -> 8 | D57: =SUMIFS('Maintenance Log'!$K$2:$K$1000,'Maintenance Log'!$I$2:$I$1000,$B57) -> 19 | E57: =SUMIFS('Maintenance Log'!$AC$2:$AC$1000,'Maintenance Log'!$I$2:$I$1000,$B57) -> 14305
B58: Corrective | C58: =COUNTIFS('Maintenance Log'!$I$2:$I$1000,$B58) -> 7 | D58: =SUMIFS('Maintenance Log'!$K$2:$K$1000,'Maintenance Log'!$I$2:$I$1000,$B58) -> 101 | E58: =SUMIFS('Maintenance Log'!$AC$2:$AC$1000,'Maintenance Log'!$I$2:$I$1000,$B58) -> 141870
B59: Overhaul | C59: =COUNTIFS('Maintenance Log'!$I$2:$I$1000,$B59) -> 0 | D59: =SUMIFS('Maintenance Log'!$K$2:$K$1000,'Maintenance Log'!$I$2:$I$1000,$B59) -> 0 | E59: =SUMIFS('Maintenance Log'!$AC$2:$AC$1000,'Maintenance Log'!$I$2:$I$1000,$B59) -> 0
B60: MAINTENANCE TREND — BY MAINTENANCE GROUP (top-level system)
B61: Maintenance Group | C61: Job Count | D61: Total Cost (ETB)
B62: I. General Service A = 5,000 KM | C62: =COUNTIFS('Maintenance Log'!$H$2:$H$1000,$B62) -> 2 | D62: =SUMIFS('Maintenance Log'!$AC$2:$AC$1000,'Maintenance Log'!$H$2:$H$1000,$B62) -> 4775
B63: I. Hydraulic System and Power Train System | C63: =COUNTIFS('Maintenance Log'!$H$2:$H$1000,$B63) -> 1 | D63: =SUMIFS('Maintenance Log'!$AC$2:$AC$1000,'Maintenance Log'!$H$2:$H$1000,$B63) -> 16840
B64: I. Hydraulic and Power Train System | C64: =COUNTIFS('Maintenance Log'!$H$2:$H$1000,$B64) -> 4 | D64: =SUMIFS('Maintenance Log'!$AC$2:$AC$1000,'Maintenance Log'!$H$2:$H$1000,$B64) -> 118500
B65: I. Inspecting, Testing and Receiving or Handover of Equipment | C65: =COUNTIFS('Maintenance Log'!$H$2:$H$1000,$B65) -> 0 | D65: =SUMIFS('Maintenance Log'!$AC$2:$AC$1000,'Maintenance Log'!$H$2:$H$1000,$B65) -> 0
B66: I. Inspecting, Testing and Receiving or Handover of Vehicles | C66: =COUNTIFS('Maintenance Log'!$H$2:$H$1000,$B66) -> 0 | D66: =SUMIFS('Maintenance Log'!$AC$2:$AC$1000,'Maintenance Log'!$H$2:$H$1000,$B66) -> 0
B67: II. Chassis Electrical Repair | C67: =COUNTIFS('Maintenance Log'!$H$2:$H$1000,$B67) -> 1 | D67: =SUMIFS('Maintenance Log'!$AC$2:$AC$1000,'Maintenance Log'!$H$2:$H$1000,$B67) -> 330
B68: II. Every 250 Service Hours or Monthly | C68: =COUNTIFS('Maintenance Log'!$H$2:$H$1000,$B68) -> 2 | D68: =SUMIFS('Maintenance Log'!$AC$2:$AC$1000,'Maintenance Log'!$H$2:$H$1000,$B68) -> 2420
B69: II. General Service B = 10,000 KM | C69: =COUNTIFS('Maintenance Log'!$H$2:$H$1000,$B69) -> 1 | D69: =SUMIFS('Maintenance Log'!$AC$2:$AC$1000,'Maintenance Log'!$H$2:$H$1000,$B69) -> 1600
B70: II. Hydraulic Hoses | C70: =COUNTIFS('Maintenance Log'!$H$2:$H$1000,$B70) -> 0 | D70: =SUMIFS('Maintenance Log'!$AC$2:$AC$1000,'Maintenance Log'!$H$2:$H$1000,$B70) -> 0
B71: III. Every 500 Service Hours or 3 months | C71: =COUNTIFS('Maintenance Log'!$H$2:$H$1000,$B71) -> 1 | D71: =SUMIFS('Maintenance Log'!$AC$2:$AC$1000,'Maintenance Log'!$H$2:$H$1000,$B71) -> 1140
B72: III. General Service C = 20,000 KM | C72: =COUNTIFS('Maintenance Log'!$H$2:$H$1000,$B72) -> 2 | D72: =SUMIFS('Maintenance Log'!$AC$2:$AC$1000,'Maintenance Log'!$H$2:$H$1000,$B72) -> 4370
B73: III. Ignition System Service | C73: =COUNTIFS('Maintenance Log'!$H$2:$H$1000,$B73) -> 0 | D73: =SUMIFS('Maintenance Log'!$AC$2:$AC$1000,'Maintenance Log'!$H$2:$H$1000,$B73) -> 0
... B103: XI. Body/Frame 0 | C103: =COUNTIFS('Maintenance Log'!$H$2:$H$1000,$B103) -> 0 | D103: =SUMIFS('Maintenance Log'!$AC$2:$AC$1000,'Maintenance Log'!$H$2:$H$1000,$B103) -> 0
B106: 💵 4. FUEL & FINANCIAL ANALYSIS BY ASSET
B108: Asset ID | C108: Fuel Norm (L/hr) | D108: Total Operable Hr | E108: Expected Fuel (L) | F108: Actual Fuel (L) | G108: Fuel Variance % | H108: Lease Rate/Hr (ETB) | I108: Total Revenue (ETB) | J108: Total Maint. Cost (ETB) | K108: Net Result (ETB) | L108: Cost per Operable Hr (ETB)
B109: ='Asset Register'!A2 -> AA-65266 | C109: ='Asset Register'!G2 -> 28 | D109: =SUMIFS('Daily Operations Log'!$G$2:$G$500,'Daily Operations Log'!$C$2:$C$500,$B109) -> 5.5 | E109: =SUMIFS('Daily Operations Log'!$Q$2:$Q$500,'Daily Operations Log'!$C$2:$C$500,$B109) -> 154 | F109: =SUMIFS('Daily Operations Log'!$P$2:$P$500,'Daily Operations Log'!$C$2:$C$500,$B109) -> 154 | G109: =IFERROR(($F109-$E109)/$E109,0) -> 0 | H109: ='Asset Register'!H2 -> 1800 | I109: =SUMIFS('Daily Operations Log'!$U$2:$U$500,'Daily Operations Log'!$C$2:$C$500,$B109) -> 9900 | J109: =SUMIFS('Maintenance Log'!$AC$2:$AC$1000,'Maintenance Log'!$C$2:$C$1000,$B109) -> 27300 | K109: =$I109-$J109 -> -17400 | L109: =IFERROR($J109/$D109,"") -> 4963.6364
B110: ='Asset Register'!A3 -> AA-65265 | C110: ='Asset Register'!G3 -> 28 | D110: =SUMIFS('Daily Operations Log'!$G$2:$G$500,'Daily Operations Log'!$C$2:$C$500,$B110) -> 0 | E110: =SUMIFS('Daily Operations Log'!$Q$2:$Q$500,'Daily Operations Log'!$C$2:$C$500,$B110) -> 0 | F110: =SUMIFS('Daily Operations Log'!$P$2:$P$500,'Daily Operations Log'!$C$2:$C$500,$B110) -> 0 | G110: =IFERROR(($F110-$E110)/$E110,0) -> 0 | H110: ='Asset Register'!H3 -> 1800 | I110: =SUMIFS('Daily Operations Log'!$U$2:$U$500,'Daily Operations Log'!$C$2:$C$500,$B110) -> 0 | J110: =SUMIFS('Maintenance Log'!$AC$2:$AC$1000,'Maintenance Log'!$C$2:$C$1000,$B110) -> 0 | K110: =$I110-$J110 -> 0 | L110: =IFERROR($J110/$D110,"")
B111: ='Asset Register'!A4 -> AA-60042 | C111: ='Asset Register'!G4 -> 28 | D111: =SUMIFS('Daily Operations Log'!$G$2:$G$500,'Daily Operations Log'!$C$2:$C$500,$B111) -> 4 | E111: =SUMIFS('Daily Operations Log'!$Q$2:$Q$500,'Daily Operations Log'!$C$2:$C$500,$B111) -> 112 | F111: =SUMIFS('Daily Operations Log'!$P$2:$P$500,'Daily Operations Log'!$C$2:$C$500,$B111) -> 120 | G111: =IFERROR(($F111-$E111)/$E111,0) -> 0.071428571 | H111: ='Asset Register'!H4 -> 1800 | I111: =SUMIFS('Daily Operations Log'!$U$2:$U$500,'Daily Operations Log'!$C$2:$C$500,$B111) -> 7200 | J111: =SUMIFS('Maintenance Log'!$AC$2:$AC$1000,'Maintenance Log'!$C$2:$C$1000,$B111) -> 800 | K111: =$I111-$J111 -> 6400 | L111: =IFERROR($J111/$D111,"") -> 200
B112: ='Asset Register'!A5 -> AA-65585 | C112: ='Asset Register'!G5 -> 24 | D112: =SUMIFS('Daily Operations Log'!$G$2:$G$500,'Daily Operations Log'!$C$2:$C$500,$B112) -> 6.5 | E112: =SUMIFS('Daily Operations Log'!$Q$2:$Q$500,'Daily Operations Log'!$C$2:$C$500,$B112) -> 156 | F112: =SUMIFS('Daily Operations Log'!$P$2:$P$500,'Daily Operations Log'!$C$2:$C$500,$B112) -> 182 | G112: =IFERROR(($F112-$E112)/$E112,0) -> 0.16666667 | H112: ='Asset Register'!H5 -> 1500 | I112: =SUMIFS('Daily Operations Log'!$U$2:$U$500,'Daily Operations Log'!$C$2:$C$500,$B112) -> 9750 | J112: =SUMIFS('Maintenance Log'!$AC$2:$AC$1000,'Maintenance Log'!$C$2:$C$1000,$B112) -> 1600 | K112: =$I112-$J112 -> 8150 | L112: =IFERROR($J112/$D112,"") -> 246.15385
B113: ='Asset Register'!A6 -> AA-9018 | C113: ='Asset Register'!G6 -> 26 | D113: =SUMIFS('Daily Operations Log'!$G$2:$G$500,'Daily Operations Log'!$C$2:$C$500,$B113) -> 5 | E113: =SUMIFS('Daily Operations Log'!$Q$2:$Q$500,'Daily Operations Log'!$C$2:$C$500,$B113) -> 130 | F113: =SUMIFS('Daily Operations Log'!$P$2:$P$500,'Daily Operations Log'!$C$2:$C$500,$B113) -> 140 | G113: =IFERROR(($F113-$E113)/$E113,0) -> 0.076923077 | H113: ='Asset Register'!H6 -> 1800 | I113: =SUMIFS('Daily Operations Log'!$U$2:$U$500,'Daily Operations Log'!$C$2:$C$500,$B113) -> 9000 | J113: =SUMIFS('Maintenance Log'!$AC$2:$AC$1000,'Maintenance Log'!$C$2:$C$1000,$B113) -> 6200 | K113: =$I113-$J113 -> 2800 | L113: =IFERROR($J113/$D113,"") -> 1240
B114: ='Asset Register'!A7 -> LV-1001 | C114: ='Asset Register'!G7 -> 12 | D114: =SUMIFS('Daily Operations Log'!$G$2:$G$500,'Daily Operations Log'!$C$2:$C$500,$B114) -> 6 | E114: =SUMIFS('Daily Operations Log'!$Q$2:$Q$500,'Daily Operations Log'!$C$2:$C$500,$B114) -> 72 | F114: =SUMIFS('Daily Operations Log'!$P$2:$P$500,'Daily Operations Log'!$C$2:$C$500,$B114) -> 75 | G114: =IFERROR(($F114-$E114)/$E114,0) -> 0.041666667 | H114: ='Asset Register'!H7 -> 450 | I114: =SUMIFS('Daily Operations Log'!$U$2:$U$500,'Daily Operations Log'!$C$2:$C$500,$B114) -> 2700 | J114: =SUMIFS('Maintenance Log'!$AC$2:$AC$1000,'Maintenance Log'!$C$2:$C$1000,$B114) -> 1475 | K114: =$I114-$J114 -> 1225 | L114: =IFERROR($J114/$D114,"") -> 245.83333
B115: ='Asset Register'!A8 -> LV-1002 | C115: ='Asset Register'!G8 -> 9 | D115: =SUMIFS('Daily Operations Log'!$G$2:$G$500,'Daily Operations Log'!$C$2:$C$500,$B115) -> 7 | E115: =SUMIFS('Daily Operations Log'!$Q$2:$Q$500,'Daily Operations Log'!$C$2:$C$500,$B115) -> 63 | F115: =SUMIFS('Daily Operations Log'!$P$2:$P$500,'Daily Operations Log'!$C$2:$C$500,$B115) -> 66 | G115: =IFERROR(($F115-$E115)/$E115,0) -> 0.047619048 | H115: ='Asset Register'!H8 -> 400 | I115: =SUMIFS('Daily Operations Log'!$U$2:$U$500,'Daily Operations Log'!$C$2:$C$500,$B115) -> 2800 | J115: =SUMIFS('Maintenance Log'!$AC$2:$AC$1000,'Maintenance Log'!$C$2:$C$1000,$B115) -> 3300 | K115: =$I115-$J115 -> -500 | L115: =IFERROR($J115/$D115,"") -> 471.42857
B116: ='Asset Register'!A9 -> LV-1003 | C116: ='Asset Register'!G9 -> 7 | D116: =SUMIFS('Daily Operations Log'!$G$2:$G$500,'Daily Operations Log'!$C$2:$C$500,$B116) -> 5 | E116: =SUMIFS('Daily Operations Log'!$Q$2:$Q$500,'Daily Operations Log'!$C$2:$C$500,$B116) -> 35 | F116: =SUMIFS('Daily Operations Log'!$P$2:$P$500,'Daily Operations Log'!$C$2:$C$500,$B116) -> 34 | G116: =IFERROR(($F116-$E116)/$E116,0) -> -0.028571429 | H116: ='Asset Register'!H9 -> 350 | I116: =SUMIFS('Daily Operations Log'!$U$2:$U$500,'Daily Operations Log'!$C$2:$C$500,$B116) -> 1750 | J116: =SUMIFS('Maintenance Log'!$AC$2:$AC$1000,'Maintenance Log'!$C$2:$C$1000,$B116) -> 450 | K116: =$I116-$J116 -> 1300 | L116: =IFERROR($J116/$D116,"") -> 90
B117: ='Asset Register'!A10 -> EX-2001 | C117: ='Asset Register'!G10 -> 22 | D117: =SUMIFS('Daily Operations Log'!$G$2:$G$500,'Daily Operations Log'!$C$2:$C$500,$B117) -> 7 | E117: =SUMIFS('Daily Operations Log'!$Q$2:$Q$500,'Daily Operations Log'!$C$2:$C$500,$B117) -> 154 | F117: =SUMIFS('Daily Operations Log'!$P$2:$P$500,'Daily Operations Log'!$C$2:$C$500,$B117) -> 158 | G117: =IFERROR(($F117-$E117)/$E117,0) -> 0.025974026 | H117: ='Asset Register'!H10 -> 2200 | I117: =SUMIFS('Daily Operations Log'!$U$2:$U$500,'Daily Operations Log'!$C$2:$C$500,$B117) -> 15400 | J117: =SUMIFS('Maintenance Log'!$AC$2:$AC$1000,'Maintenance Log'!$C$2:$C$1000,$B117) -> 84000 | K117: =$I117-$J117 -> -68600 | L117: =IFERROR($J117/$D117,"") -> 12000
B118: ='Asset Register'!A11 -> GD-3001 | C118: ='Asset Register'!G11 -> 20 | D118: =SUMIFS('Daily Operations Log'!$G$2:$G$500,'Daily Operations Log'!$C$2:$C$500,$B118) -> 6 | E118: =SUMIFS('Daily Operations Log'!$Q$2:$Q$500,'Daily Operations Log'!$C$2:$C$500,$B118) -> 120 | F118: =SUMIFS('Daily Operations Log'!$P$2:$P$500,'Daily Operations Log'!$C$2:$C$500,$B118) -> 128 | G118: =IFERROR(($F118-$E118)/$E118,0) -> 0.066666667 | H118: ='Asset Register'!H11 -> 2000 | I118: =SUMIFS('Daily Operations Log'!$U$2:$U$500,'Daily Operations Log'!$C$2:$C$500,$B118) -> 12000 | J118: =SUMIFS('Maintenance Log'!$AC$2:$AC$1000,'Maintenance Log'!$C$2:$C$1000,$B118) -> 16840 | K118: =$I118-$J118 -> -4840 | L118: =IFERROR($J118/$D118,"") -> 2806.6667
B119: ='Asset Register'!A12 -> LD-4001 | C119: ='Asset Register'!G12 -> 18 | D119: =SUMIFS('Daily Operations Log'!$G$2:$G$500,'Daily Operations Log'!$C$2:$C$500,$B119) -> 6.5 | E119: =SUMIFS('Daily Operations Log'!$Q$2:$Q$500,'Daily Operations Log'!$C$2:$C$500,$B119) -> 117 | F119: =SUMIFS('Daily Operations Log'!$P$2:$P$500,'Daily Operations Log'!$C$2:$C$500,$B119) -> 122 | G119: =IFERROR(($F119-$E119)/$E119,0) -> 0.042735043 | H119: ='Asset Register'!H12 -> 1900 | I119: =SUMIFS('Daily Operations Log'!$U$2:$U$500,'Daily Operations Log'!$C$2:$C$500,$B119) -> 12350 | J119: =SUMIFS('Maintenance Log'!$AC$2:$AC$1000,'Maintenance Log'!$C$2:$C$1000,$B119) -> 7200 | K119: =$I119-$J119 -> 5150 | L119: =IFERROR($J119/$D119,"") -> 1107.6923
B120: ='Asset Register'!A13 -> GN-5001 | C120: ='Asset Register'!G13 -> 12 | D120: =SUMIFS('Daily Operations Log'!$G$2:$G$500,'Daily Operations Log'!$C$2:$C$500,$B120) -> 8 | E120: =SUMIFS('Daily Operations Log'!$Q$2:$Q$500,'Daily Operations Log'!$C$2:$C$500,$B120) -> 96 | F120: =SUMIFS('Daily Operations Log'!$P$2:$P$500,'Daily Operations Log'!$C$2:$C$500,$B120) -> 100 | G120: =IFERROR(($F120-$E120)/$E120,0) -> 0.041666667 | H120: ='Asset Register'!H13 -> 300 | I120: =SUMIFS('Daily Operations Log'!$U$2:$U$500,'Daily Operations Log'!$C$2:$C$500,$B120) -> 2400 | J120: =SUMIFS('Maintenance Log'!$AC$2:$AC$1000,'Maintenance Log'!$C$2:$C$1000,$B120) -> 1620 | K120: =$I120-$J120 -> 780 | L120: =IFERROR($J120/$D120,"") -> 202.5
... B123: ='Asset Register'!A16 -> EL-8001 | C123: ='Asset Register'!G16 -> 0 | D123: =SUMIFS('Daily Operations Log'!$G$2:$G$500,'Daily Operations Log'!$C$2:$C$500,$B123) -> 8 | E123: =SUMIFS('Daily Operations Log'!$Q$2:$Q$500,'Daily Operations Log'!$C$2:$C$500,$B123) -> 0 | F123: =SUMIFS('Daily Operations Log'!$P$2:$P$500,'Daily Operations Log'!$C$2:$C$500,$B123) -> 0 | G123: =IFERROR(($F123-$E123)/$E123,0) -> 0 | H123: ='Asset Register'!H16 -> 200 | I123: =SUMIFS('Daily Operations Log'!$U$2:$U$500,'Daily Operations Log'!$C$2:$C$500,$B123) -> 1600 | J123: =SUMIFS('Maintenance Log'!$AC$2:$AC$1000,'Maintenance Log'!$C$2:$C$1000,$B123) -> 330 | K123: =$I123-$J123 -> 1270 | L123: =IFERROR($J123/$D123,"") -> 41.25
B126: 🎯 5. FLEET OPTIMIZATION RECOMMENDATIONS
B128: Asset ID | C128: Availability Status | D128: Utilization Status | E128: Fuel Efficiency | F128: Maintenance Priority | G128: Recommendation
B129: =$B17 -> AA-65266 | C129: =IF($H17="","No data",IF($H17>=0.9,"Good",IF($H17>=0.7,"Moderate","Low"))) -> Good | D129: =IF($I17="","No data",IF($I17>=0.7,"Good",IF($I17>=0.4,"Moderate","Underutilized"))) -> Moderate | E129: =IF($G109="","No data",IF(ABS($G109)>0.1,"Overconsuming","Normal")) -> Normal | F129: =IF($D37>0.3,"Critical",IF($D37>0,"Watch","OK")) -> Watch | G129: =IF($F129="Critical","Prioritize repair / consider replacement",IF($E129="Overconsuming","Investigate fuel use or operator behavior",IF($D129="Underutilized","Reassign or reduce lease commitment",IF($C129="Low","Schedule preventive service","Operating normally")))) -> Operating normally
B130: =$B18 -> AA-65265 | C130: =IF($H18="","No data",IF($H18>=0.9,"Good",IF($H18>=0.7,"Moderate","Low"))) -> Low | D130: =IF($I18="","No data",IF($I18>=0.7,"Good",IF($I18>=0.4,"Moderate","Underutilized"))) -> Underutilized | E130: =IF($G110="","No data",IF(ABS($G110)>0.1,"Overconsuming","Normal")) -> Normal | F130: =IF($D38>0.3,"Critical",IF($D38>0,"Watch","OK")) -> Critical | G130: =IF($F130="Critical","Prioritize repair / consider replacement",IF($E130="Overconsuming","Investigate fuel use or operator behavior",IF($D130="Underutilized","Reassign or reduce lease commitment",IF($C130="Low","Schedule preventive service","Operating normally")))) -> Prioritize repair / consider replacement
B131: =$B19 -> AA-60042 | C131: =IF($H19="","No data",IF($H19>=0.9,"Good",IF($H19>=0.7,"Moderate","Low"))) -> Good | D131: =IF($I19="","No data",IF($I19>=0.7,"Good",IF($I19>=0.4,"Moderate","Underutilized"))) -> Moderate | E131: =IF($G111="","No data",IF(ABS($G111)>0.1,"Overconsuming","Normal")) -> Normal | F131: =IF($D39>0.3,"Critical",IF($D39>0,"Watch","OK")) -> OK | G131: =IF($F131="Critical","Prioritize repair / consider replacement",IF($E131="Overconsuming","Investigate fuel use or operator behavior",IF($D131="Underutilized","Reassign or reduce lease commitment",IF($C131="Low","Schedule preventive service","Operating normally")))) -> Operating normally
B132: =$B20 -> AA-65585 | C132: =IF($H20="","No data",IF($H20>=0.9,"Good",IF($H20>=0.7,"Moderate","Low"))) -> Good | D132: =IF($I20="","No data",IF($I20>=0.7,"Good",IF($I20>=0.4,"Moderate","Underutilized"))) -> Good | E132: =IF($G112="","No data",IF(ABS($G112)>0.1,"Overconsuming","Normal")) -> Overconsuming | F132: =IF($D40>0.3,"Critical",IF($D40>0,"Watch","OK")) -> OK | G132: =IF($F132="Critical","Prioritize repair / consider replacement",IF($E132="Overconsuming","Investigate fuel use or operator behavior",IF($D132="Underutilized","Reassign or reduce lease commitment",IF($C132="Low","Schedule preventive service","Operating normally")))) -> Investigate fuel use or operator behavior
B133: =$B21 -> AA-9018 | C133: =IF($H21="","No data",IF($H21>=0.9,"Good",IF($H21>=0.7,"Moderate","Low"))) -> Moderate | D133: =IF($I21="","No data",IF($I21>=0.7,"Good",IF($I21>=0.4,"Moderate","Underutilized"))) -> Moderate | E133: =IF($G113="","No data",IF(ABS($G113)>0.1,"Overconsuming","Normal")) -> Normal | F133: =IF($D41>0.3,"Critical",IF($D41>0,"Watch","OK")) -> Watch | G133: =IF($F133="Critical","Prioritize repair / consider replacement",IF($E133="Overconsuming","Investigate fuel use or operator behavior",IF($D133="Underutilized","Reassign or reduce lease commitment",IF($C133="Low","Schedule preventive service","Operating normally")))) -> Operating normally
B134: =$B22 -> LV-1001 | C134: =IF($H22="","No data",IF($H22>=0.9,"Good",IF($H22>=0.7,"Moderate","Low"))) -> Good | D134: =IF($I22="","No data",IF($I22>=0.7,"Good",IF($I22>=0.4,"Moderate","Underutilized"))) -> Good | E134: =IF($G114="","No data",IF(ABS($G114)>0.1,"Overconsuming","Normal")) -> Normal | F134: =IF($D42>0.3,"Critical",IF($D42>0,"Watch","OK")) -> OK | G134: =IF($F134="Critical","Prioritize repair / consider replacement",IF($E134="Overconsuming","Investigate fuel use or operator behavior",IF($D134="Underutilized","Reassign or reduce lease commitment",IF($C134="Low","Schedule preventive service","Operating normally")))) -> Operating normally
B135: =$B23 -> LV-1002 | C135: =IF($H23="","No data",IF($H23>=0.9,"Good",IF($H23>=0.7,"Moderate","Low"))) -> Good | D135: =IF($I23="","No data",IF($I23>=0.7,"Good",IF($I23>=0.4,"Moderate","Underutilized"))) -> Good | E135: =IF($G115="","No data",IF(ABS($G115)>0.1,"Overconsuming","Normal")) -> Normal | F135: =IF($D43>0.3,"Critical",IF($D43>0,"Watch","OK")) -> OK | G135: =IF($F135="Critical","Prioritize repair / consider replacement",IF($E135="Overconsuming","Investigate fuel use or operator behavior",IF($D135="Underutilized","Reassign or reduce lease commitment",IF($C135="Low","Schedule preventive service","Operating normally")))) -> Operating normally
B136: =$B24 -> LV-1003 | C136: =IF($H24="","No data",IF($H24>=0.9,"Good",IF($H24>=0.7,"Moderate","Low"))) -> Good | D136: =IF($I24="","No data",IF($I24>=0.7,"Good",IF($I24>=0.4,"Moderate","Underutilized"))) -> Good | E136: =IF($G116="","No data",IF(ABS($G116)>0.1,"Overconsuming","Normal")) -> Normal | F136: =IF($D44>0.3,"Critical",IF($D44>0,"Watch","OK")) -> OK | G136: =IF($F136="Critical","Prioritize repair / consider replacement",IF($E136="Overconsuming","Investigate fuel use or operator behavior",IF($D136="Underutilized","Reassign or reduce lease commitment",IF($C136="Low","Schedule preventive service","Operating normally")))) -> Operating normally
B137: =$B25 -> EX-2001 | C137: =IF($H25="","No data",IF($H25>=0.9,"Good",IF($H25>=0.7,"Moderate","Low"))) -> Good | D137: =IF($I25="","No data",IF($I25>=0.7,"Good",IF($I25>=0.4,"Moderate","Underutilized"))) -> Good | E137: =IF($G117="","No data",IF(ABS($G117)>0.1,"Overconsuming","Normal")) -> Normal | F137: =IF($D45>0.3,"Critical",IF($D45>0,"Watch","OK")) -> OK | G137: =IF($F137="Critical","Prioritize repair / consider replacement",IF($E137="Overconsuming","Investigate fuel use or operator behavior",IF($D137="Underutilized","Reassign or reduce lease commitment",IF($C137="Low","Schedule preventive service","Operating normally")))) -> Operating normally
B138: =$B26 -> GD-3001 | C138: =IF($H26="","No data",IF($H26>=0.9,"Good",IF($H26>=0.7,"Moderate","Low"))) -> Good | D138: =IF($I26="","No data",IF($I26>=0.7,"Good",IF($I26>=0.4,"Moderate","Underutilized"))) -> Good | E138: =IF($G118="","No data",IF(ABS($G118)>0.1,"Overconsuming","Normal")) -> Normal | F138: =IF($D46>0.3,"Critical",IF($D46>0,"Watch","OK")) -> OK | G138: =IF($F138="Critical","Prioritize repair / consider replacement",IF($E138="Overconsuming","Investigate fuel use or operator behavior",IF($D138="Underutilized","Reassign or reduce lease commitment",IF($C138="Low","Schedule preventive service","Operating normally")))) -> Operating normally
B139: =$B27 -> LD-4001 | C139: =IF($H27="","No data",IF($H27>=0.9,"Good",IF($H27>=0.7,"Moderate","Low"))) -> Good | D139: =IF($I27="","No data",IF($I27>=0.7,"Good",IF($I27>=0.4,"Moderate","Underutilized"))) -> Good | E139: =IF($G119="","No data",IF(ABS($G119)>0.1,"Overconsuming","Normal")) -> Normal | F139: =IF($D47>0.3,"Critical",IF($D47>0,"Watch","OK")) -> OK | G139: =IF($F139="Critical","Prioritize repair / consider replacement",IF($E139="Overconsuming","Investigate fuel use or operator behavior",IF($D139="Underutilized","Reassign or reduce lease commitment",IF($C139="Low","Schedule preventive service","Operating normally")))) -> Operating normally
B140: =$B28 -> GN-5001 | C140: =IF($H28="","No data",IF($H28>=0.9,"Good",IF($H28>=0.7,"Moderate","Low"))) -> Good | D140: =IF($I28="","No data",IF($I28>=0.7,"Good",IF($I28>=0.4,"Moderate","Underutilized"))) -> Good | E140: =IF($G120="","No data",IF(ABS($G120)>0.1,"Overconsuming","Normal")) -> Normal | F140: =IF($D48>0.3,"Critical",IF($D48>0,"Watch","OK")) -> OK | G140: =IF($F140="Critical","Prioritize repair / consider replacement",IF($E140="Overconsuming","Investigate fuel use or operator behavior",IF($D140="Underutilized","Reassign or reduce lease commitment",IF($C140="Low","Schedule preventive service","Operating normally")))) -> Operating normally
... B143: =$B31 -> EL-8001 | C143: =IF($H31="","No data",IF($H31>=0.9,"Good",IF($H31>=0.7,"Moderate","Low"))) -> Good | D143: =IF($I31="","No data",IF($I31>=0.7,"Good",IF($I31>=0.4,"Moderate","Underutilized"))) -> Good | E143: =IF($G123="","No data",IF(ABS($G123)>0.1,"Overconsuming","Normal")) -> Normal | F143: =IF($D51>0.3,"Critical",IF($D51>0,"Watch","OK")) -> OK | G143: =IF($F143="Critical","Prioritize repair / consider replacement",IF($E143="Overconsuming","Investigate fuel use or operator behavior",IF($D143="Underutilized","Reassign or reduce lease commitment",IF($C143="Low","Schedule preventive service","Operating normally")))) -> Operating normally
B146: Note: All figures are formula-driven from Asset Register, Daily Operations Log, and Maintenance Log. For a breakdown by individual task (which of the 858 standardized tasks recurs most), insert a PivotTable from the Maintenance Log table once real data is loaded -- see the Read Me sheet.
